{
  "pageId": "1123521b-014a-8007-a56e-ea4e916ca7f4",
  "lastEditedAt": "2024-10-01T00:57:00.000Z",
  "slug": "read-books-2024-q3",
  "locale": "ja",
  "properties": {
    "title": "読んだ本 2024-Q3",
    "date": "2024-10-01T00:56:00.000Z",
    "category": "Diary",
    "tags": ["読書"]
  },
  "content": [
    {
      "type": "paragraph",
      "text": [
        {
          "type": "text",
          "text": "2024年 7月〜9月に読んだ本・読んでいる本",
          "annotations": {}
        }
      ]
    },
    {
      "type": "paragraph",
      "text": []
    },
    {
      "type": "image",
      "external": false,
      "path": "read-books-2024-q3/3c6255ea-b6c7-4055-8126-638d2819f0c3/32577442-6ab9-495c-a9ab-f1e76d99ac81.png",
      "caption": ""
    },
    {
      "type": "paragraph",
      "text": []
    },
    {
      "type": "paragraph",
      "text": [
        {
          "type": "text",
          "text": "今回は9冊とそこそこのペースを保って読めた。",
          "annotations": {}
        }
      ]
    },
    {
      "type": "paragraph",
      "text": []
    },
    {
      "type": "heading",
      "level": 2,
      "text": [
        {
          "type": "text",
          "text": "「論理的思考」の文化的基盤",
          "annotations": {}
        }
      ]
    },
    {
      "type": "paragraph",
      "text": []
    },
    {
      "type": "link_preview",
      "url": "https://amzn.asia/d/6mQ6F21"
    },
    {
      "type": "paragraph",
      "text": [
        {
          "type": "text",
          "text": "まだ3割くらいの進捗だが、すでに自分の中の「論理的思考」観をかなり破壊してくれる。はやく読み切りたい。",
          "annotations": {}
        }
      ]
    },
    {
      "type": "heading",
      "level": 2,
      "text": [
        {
          "type": "text",
          "text": "忘却の効用",
          "annotations": {}
        }
      ]
    },
    {
      "type": "link_preview",
      "url": "https://amzn.asia/d/20laD56"
    },
    {
      "type": "paragraph",
      "text": [
        {
          "type": "text",
          "text": "ゆる言語学ラジオの水野さんが推していたので読んでみたが、「忘却」という現象への新しい考え方が得られたし、とてもおもしろかった。文章に翻訳書の味が強すぎるのがちょっと惜しい。",
          "annotations": {}
        }
      ]
    },
    {
      "type": "heading",
      "level": 2,
      "text": [
        {
          "type": "text",
          "text": "なぜ私たちは燃え尽きてしまうのか",
          "annotations": {}
        }
      ]
    },
    {
      "type": "link_preview",
      "url": "https://amzn.asia/d/bcH5zSA"
    },
    {
      "type": "paragraph",
      "text": [
        {
          "type": "text",
          "text": "いまのところ今年のベストブック。うかつに読むと人生を破壊されるパワーがある。一度読んでしまうとこの本を読む前の考え方には戻れなくなるような、そういう破壊力があるのでそうやすやすとはおすすめしにくい。しかし確実にこの本は「よく生きる」ための本である。",
          "annotations": {}
        }
      ]
    },
    {
      "type": "heading",
      "level": 2,
      "text": [
        {
          "type": "text",
          "text": "「無理」の構造　この世の理不尽さを可視化する",
          "annotations": {}
        }
      ]
    },
    {
      "type": "link_preview",
      "url": "https://amzn.asia/d/4beTSM9"
    },
    {
      "type": "paragraph",
      "text": [
        {
          "type": "text",
          "text": "「具体と抽象」の細谷功さんの本。読んでみたものの自分向けではなかった。社会人経験が浅めの、生きづらさを感じている時期に読むと道が開けるような感じで、まあ自己啓発本と言っていい。読みやすいので伸び悩み始めた若手なんかにおすすめするといいのではないか。",
          "annotations": {}
        }
      ]
    },
    {
      "type": "heading",
      "level": 2,
      "text": [
        {
          "type": "text",
          "text": "ネガティブ・ケイパビリティ　答えの出ない事態に耐える力",
          "annotations": {}
        }
      ]
    },
    {
      "type": "link_preview",
      "url": "https://amzn.asia/d/5KDtmVH"
    },
    {
      "type": "paragraph",
      "text": [
        {
          "type": "text",
          "text": "「心理的安全性」につづき「ネガティブ・ケイパビリティ」もややバズワード化しつつある昨今だが、2017年に書かれたこの本はおそらく日本語でネガティブ・ケイパビリティに書かれたパイオニア的一冊だと思われるし、おそらく「原義」のネイティブ・ケイパビリティについて緻密に書かれており、この本を読まずして語るとしたら完全にエアプだろうと思った。勉強になったし、読み物としてもおもしろかった。",
          "annotations": {}
        }
      ]
    },
    {
      "type": "heading",
      "level": 2,
      "text": [
        {
          "type": "text",
          "text": "いつもの言葉を哲学する",
          "annotations": {}
        }
      ]
    },
    {
      "type": "link_preview",
      "url": "https://amzn.asia/d/93Iqnpu"
    },
    {
      "type": "paragraph",
      "text": [
        {
          "type": "text",
          "text": "積読していた一冊。古田徹也ファンなのでいつもどおりおもしろかったが、新書ということもあり他の著作のエッセンスが寄せ集められた感じもあり、ファンとしては新鮮味はあまり感じなかった。2021年の著作ということもあり、後半のコロナ禍の言葉についての記述が熱が入っており、おそらくこれを書きたかった一冊だろうと思う。",
          "annotations": {}
        }
      ]
    },
    {
      "type": "heading",
      "level": 2,
      "text": [
        {
          "type": "text",
          "text": "進化的アーキテクチャ",
          "annotations": {}
        }
      ]
    },
    {
      "type": "link_preview",
      "url": "https://amzn.asia/d/3xgNZav"
    },
    {
      "type": "paragraph",
      "text": [
        {
          "type": "text",
          "text": "リファラジのネタになるかと思って読んでみたが、あまり刺さらなかった。",
          "annotations": {}
        }
      ]
    },
    {
      "type": "heading",
      "level": 2,
      "text": [
        {
          "type": "text",
          "text": "言語哲学がはじまる",
          "annotations": {}
        }
      ]
    },
    {
      "type": "link_preview",
      "url": "https://amzn.asia/d/9l66y5l"
    },
    {
      "type": "paragraph",
      "text": [
        {
          "type": "text",
          "text": "去年話題になった新書で、積読していた。言語哲学がどうはじまり、どう進んできたのか。特にフレーゲ、ラッセルを踏まえてウィトゲンシュタインの言語哲学にどうたどり着くのかという展開を描いている。新書なのでかなり易しく書かれていて哲学書慣れしていない人におすすめもしやすそうである。",
          "annotations": {}
        }
      ]
    },
    {
      "type": "heading",
      "level": 2,
      "text": [
        {
          "type": "text",
          "text": "13歳から鍛える具体と抽象",
          "annotations": {}
        }
      ]
    },
    {
      "type": "link_preview",
      "url": "https://amzn.asia/d/6MsnHJ7"
    },
    {
      "type": "paragraph",
      "text": [
        {
          "type": "text",
          "text": "この本はマジでよかった。読んだきっかけはMagnoliaさんのブログ。",
          "annotations": {}
        }
      ]
    },
    {
      "type": "link_preview",
      "url": "https://blog.magnolia.tech/entry/2024/07/02/003045"
    },
    {
      "type": "paragraph",
      "text": [
        {
          "type": "text",
          "text": "これ会得してなかったら13歳以下の設計力ということでいいでしょう。大人も今すぐ読むべき。",
          "annotations": {}
        }
      ]
    }
  ]
}
