[{"object":"block","id":"cc95c45b-366f-4b20-bc25-af47db8be2fc","parent":{"type":"page_id","page_id":"ba94cfed-9b64-41d3-862b-55c25fe0cea7"},"created_time":"2023-05-21T00:22:00.000Z","last_edited_time":"2023-05-21T00:22:00.000Z","created_by":{"object":"user","id":"f4f222d4-d508-405d-ba6c-da82ee26ee54"},"last_edited_by":{"object":"user","id":"f4f222d4-d508-405d-ba6c-da82ee26ee54"},"has_children":false,"archived":false,"in_trash":false,"type":"paragraph","paragraph":{"rich_text":[{"type":"text","text":{"content":"This article will explain how to create an environment for Angular 2 testing. It uses ","link":null},"annotations":{"bold":false,"italic":false,"strikethrough":false,"underline":false,"code":false,"color":"default"},"plain_text":"This article will explain how to create an environment for Angular 2 testing. It uses ","href":null},{"type":"text","text":{"content":"Karma","link":{"url":"https://karma-runner.github.io/1.0/index.html"}},"annotations":{"bold":false,"italic":false,"strikethrough":false,"underline":false,"code":false,"color":"default"},"plain_text":"Karma","href":"https://karma-runner.github.io/1.0/index.html"},{"type":"text","text":{"content":", ","link":null},"annotations":{"bold":false,"italic":false,"strikethrough":false,"underline":false,"code":false,"color":"default"},"plain_text":", ","href":null},{"type":"text","text":{"content":"webpack","link":{"url":"http://webpack.js.org/"}},"annotations":{"bold":false,"italic":false,"strikethrough":false,"underline":false,"code":false,"color":"default"},"plain_text":"webpack","href":"http://webpack.js.org/"},{"type":"text","text":{"content":" and some useful stuffs. And it focuses on simplicity and ease to use. Let’s understand it step by step.","link":null},"annotations":{"bold":false,"italic":false,"strikethrough":false,"underline":false,"code":false,"color":"default"},"plain_text":" and some useful stuffs. And it focuses on simplicity and ease to use. Let’s understand it step by step.","href":null}],"color":"default"}},{"object":"block","id":"2a90fd23-fd13-40de-9a53-948d3319895d","parent":{"type":"page_id","page_id":"ba94cfed-9b64-41d3-862b-55c25fe0cea7"},"created_time":"2023-05-21T00:22:00.000Z","last_edited_time":"2023-05-21T00:22:00.000Z","created_by":{"object":"user","id":"f4f222d4-d508-405d-ba6c-da82ee26ee54"},"last_edited_by":{"object":"user","id":"f4f222d4-d508-405d-ba6c-da82ee26ee54"},"has_children":false,"archived":false,"in_trash":false,"type":"heading_2","heading_2":{"rich_text":[{"type":"text","text":{"content":"Create an Application (no tests)","link":null},"annotations":{"bold":false,"italic":false,"strikethrough":false,"underline":false,"code":false,"color":"default"},"plain_text":"Create an Application (no tests)","href":null}],"is_toggleable":false,"color":"default"}},{"object":"block","id":"00feab7e-8b22-43f3-9738-0f670c896ea7","parent":{"type":"page_id","page_id":"ba94cfed-9b64-41d3-862b-55c25fe0cea7"},"created_time":"2023-05-21T00:22:00.000Z","last_edited_time":"2023-05-21T00:22:00.000Z","created_by":{"object":"user","id":"f4f222d4-d508-405d-ba6c-da82ee26ee54"},"last_edited_by":{"object":"user","id":"f4f222d4-d508-405d-ba6c-da82ee26ee54"},"has_children":false,"archived":false,"in_trash":false,"type":"code","code":{"caption":[],"rich_text":[{"type":"text","text":{"content":"> npm init -y\n> npm i -S @angular/{core,common,compiler,platform-browser,platform-browser-dynamic} rxjs zone.js core-js\n> npm i -D typescript webpack@~2.1.0-beta awesome-typescript-loader angular2-template-loader raw-loader node-static @types/node\n> $(npm bin)/tsc --init\n> touch webpack.config.js index.html\n> mkdir src\n> touch src/main.ts src/app.module.ts src/app.component.ts src/app.component.html","link":null},"annotations":{"bold":false,"italic":false,"strikethrough":false,"underline":false,"code":false,"color":"default"},"plain_text":"> npm init -y\n> npm i -S @angular/{core,common,compiler,platform-browser,platform-browser-dynamic} rxjs zone.js core-js\n> npm i -D typescript webpack@~2.1.0-beta awesome-typescript-loader angular2-template-loader raw-loader node-static @types/node\n> $(npm bin)/tsc --init\n> touch webpack.config.js index.html\n> mkdir src\n> touch src/main.ts src/app.module.ts src/app.component.ts src/app.component.html","href":null}],"language":"plain text"}},{"object":"block","id":"e0230293-9ec2-442e-be11-fc9b2720db7a","parent":{"type":"page_id","page_id":"ba94cfed-9b64-41d3-862b-55c25fe0cea7"},"created_time":"2023-05-21T00:22:00.000Z","last_edited_time":"2023-05-21T00:22:00.000Z","created_by":{"object":"user","id":"f4f222d4-d508-405d-ba6c-da82ee26ee54"},"last_edited_by":{"object":"user","id":"f4f222d4-d508-405d-ba6c-da82ee26ee54"},"has_children":false,"archived":false,"in_trash":false,"type":"paragraph","paragraph":{"rich_text":[{"type":"text","text":{"content":"app.component.ts:","link":null},"annotations":{"bold":false,"italic":false,"strikethrough":false,"underline":false,"code":false,"color":"default"},"plain_text":"app.component.ts:","href":null}],"color":"default"}},{"object":"block","id":"5538e9b3-9be8-4940-9923-46c08e8b3049","parent":{"type":"page_id","page_id":"ba94cfed-9b64-41d3-862b-55c25fe0cea7"},"created_time":"2023-05-21T00:22:00.000Z","last_edited_time":"2023-05-21T01:33:00.000Z","created_by":{"object":"user","id":"f4f222d4-d508-405d-ba6c-da82ee26ee54"},"last_edited_by":{"object":"user","id":"f4f222d4-d508-405d-ba6c-da82ee26ee54"},"has_children":false,"archived":false,"in_trash":false,"type":"code","code":{"caption":[],"rich_text":[{"type":"text","text":{"content":"import { Component } from \"@angular/core\";\n@Component({\n  selector: \"my-app\",\n  templateUrl: \"app.component.html\"\n})\nexport class AppComponent {}","link":null},"annotations":{"bold":false,"italic":false,"strikethrough":false,"underline":false,"code":false,"color":"default"},"plain_text":"import { Component } from \"@angular/core\";\n@Component({\n  selector: \"my-app\",\n  templateUrl: \"app.component.html\"\n})\nexport class AppComponent {}","href":null}],"language":"plain text"}},{"object":"block","id":"9aba0828-f6fd-42c5-b450-0830b2fe3452","parent":{"type":"page_id","page_id":"ba94cfed-9b64-41d3-862b-55c25fe0cea7"},"created_time":"2023-05-21T00:22:00.000Z","last_edited_time":"2023-05-21T00:22:00.000Z","created_by":{"object":"user","id":"f4f222d4-d508-405d-ba6c-da82ee26ee54"},"last_edited_by":{"object":"user","id":"f4f222d4-d508-405d-ba6c-da82ee26ee54"},"has_children":false,"archived":false,"in_trash":false,"type":"paragraph","paragraph":{"rich_text":[{"type":"text","text":{"content":"app.module.ts:","link":null},"annotations":{"bold":false,"italic":false,"strikethrough":false,"underline":false,"code":false,"color":"default"},"plain_text":"app.module.ts:","href":null}],"color":"default"}},{"object":"block","id":"517be317-ac89-4e63-8434-0520e1b22d36","parent":{"type":"page_id","page_id":"ba94cfed-9b64-41d3-862b-55c25fe0cea7"},"created_time":"2023-05-21T00:22:00.000Z","last_edited_time":"2023-05-21T01:33:00.000Z","created_by":{"object":"user","id":"f4f222d4-d508-405d-ba6c-da82ee26ee54"},"last_edited_by":{"object":"user","id":"f4f222d4-d508-405d-ba6c-da82ee26ee54"},"has_children":false,"archived":false,"in_trash":false,"type":"code","code":{"caption":[],"rich_text":[{"type":"text","text":{"content":"import { NgModule } from \"@angular/core\";\nimport { BrowserModule } from \"@angular/platform-browser\";\nimport { AppComponent } from \"./app.component\";\n@NgModule({\n  imports: [BrowserModule],\n  declarations: [AppComponent],\n  bootstrap: [AppComponent]\n})\nexport class AppModule {}","link":null},"annotations":{"bold":false,"italic":false,"strikethrough":false,"underline":false,"code":false,"color":"default"},"plain_text":"import { NgModule } from \"@angular/core\";\nimport { BrowserModule } from \"@angular/platform-browser\";\nimport { AppComponent } from \"./app.component\";\n@NgModule({\n  imports: [BrowserModule],\n  declarations: [AppComponent],\n  bootstrap: [AppComponent]\n})\nexport class AppModule {}","href":null}],"language":"plain text"}},{"object":"block","id":"0edfada4-6bb8-411f-8196-29bbaf2f513f","parent":{"type":"page_id","page_id":"ba94cfed-9b64-41d3-862b-55c25fe0cea7"},"created_time":"2023-05-21T00:22:00.000Z","last_edited_time":"2023-05-21T00:22:00.000Z","created_by":{"object":"user","id":"f4f222d4-d508-405d-ba6c-da82ee26ee54"},"last_edited_by":{"object":"user","id":"f4f222d4-d508-405d-ba6c-da82ee26ee54"},"has_children":false,"archived":false,"in_trash":false,"type":"paragraph","paragraph":{"rich_text":[{"type":"text","text":{"content":"main.ts:","link":null},"annotations":{"bold":false,"italic":false,"strikethrough":false,"underline":false,"code":false,"color":"default"},"plain_text":"main.ts:","href":null}],"color":"default"}},{"object":"block","id":"fa593748-1eae-416b-83d4-df8271a21006","parent":{"type":"page_id","page_id":"ba94cfed-9b64-41d3-862b-55c25fe0cea7"},"created_time":"2023-05-21T00:22:00.000Z","last_edited_time":"2023-05-21T01:33:00.000Z","created_by":{"object":"user","id":"f4f222d4-d508-405d-ba6c-da82ee26ee54"},"last_edited_by":{"object":"user","id":"f4f222d4-d508-405d-ba6c-da82ee26ee54"},"has_children":false,"archived":false,"in_trash":false,"type":"code","code":{"caption":[],"rich_text":[{"type":"text","text":{"content":"import \"core-js\";\nimport \"zone.js/dist/zone\";\nimport { platformBrowserDynamic } from \"@angular/platform-browser-dynamic\";\nimport { AppModule } from \"./app.module\";\nplatformBrowserDynamic().bootstrapModule(AppModule);","link":null},"annotations":{"bold":false,"italic":false,"strikethrough":false,"underline":false,"code":false,"color":"default"},"plain_text":"import \"core-js\";\nimport \"zone.js/dist/zone\";\nimport { platformBrowserDynamic } from \"@angular/platform-browser-dynamic\";\nimport { AppModule } from \"./app.module\";\nplatformBrowserDynamic().bootstrapModule(AppModule);","href":null}],"language":"plain text"}},{"object":"block","id":"ba5428c0-8800-45d2-b986-0f3837c0bdc6","parent":{"type":"page_id","page_id":"ba94cfed-9b64-41d3-862b-55c25fe0cea7"},"created_time":"2023-05-21T00:22:00.000Z","last_edited_time":"2023-05-21T00:22:00.000Z","created_by":{"object":"user","id":"f4f222d4-d508-405d-ba6c-da82ee26ee54"},"last_edited_by":{"object":"user","id":"f4f222d4-d508-405d-ba6c-da82ee26ee54"},"has_children":false,"archived":false,"in_trash":false,"type":"paragraph","paragraph":{"rich_text":[{"type":"text","text":{"content":"tsconfig.json:","link":null},"annotations":{"bold":false,"italic":false,"strikethrough":false,"underline":false,"code":false,"color":"default"},"plain_text":"tsconfig.json:","href":null}],"color":"default"}},{"object":"block","id":"201b171c-66e0-4cf0-b999-03e234ba722a","parent":{"type":"page_id","page_id":"ba94cfed-9b64-41d3-862b-55c25fe0cea7"},"created_time":"2023-05-21T00:22:00.000Z","last_edited_time":"2023-05-21T01:33:00.000Z","created_by":{"object":"user","id":"f4f222d4-d508-405d-ba6c-da82ee26ee54"},"last_edited_by":{"object":"user","id":"f4f222d4-d508-405d-ba6c-da82ee26ee54"},"has_children":false,"archived":false,"in_trash":false,"type":"code","code":{"caption":[],"rich_text":[{"type":"text","text":{"content":"{\n  \"compilerOptions\": {\n    \"module\": \"es2015\",\n    \"target\": \"es5\",\n    \"noImplicitAny\": false,\n    \"sourceMap\": true,\n    \"moduleResolution\": \"node\",\n    \"experimentalDecorators\": true,\n    \"emitDecoratorMetadata\": true,\n    \"lib\": [\"es2015\", \"dom\"],\n    \"types\": [\"node\"]\n  },\n  \"awesomeTypeScriptLoaderOptions\": {\n    \"useWebpackText\": true\n  }\n}","link":null},"annotations":{"bold":false,"italic":false,"strikethrough":false,"underline":false,"code":false,"color":"default"},"plain_text":"{\n  \"compilerOptions\": {\n    \"module\": \"es2015\",\n    \"target\": \"es5\",\n    \"noImplicitAny\": false,\n    \"sourceMap\": true,\n    \"moduleResolution\": \"node\",\n    \"experimentalDecorators\": true,\n    \"emitDecoratorMetadata\": true,\n    \"lib\": [\"es2015\", \"dom\"],\n    \"types\": [\"node\"]\n  },\n  \"awesomeTypeScriptLoaderOptions\": {\n    \"useWebpackText\": true\n  }\n}","href":null}],"language":"json"}},{"object":"block","id":"de504312-fd85-414f-a512-0ce29a3b6066","parent":{"type":"page_id","page_id":"ba94cfed-9b64-41d3-862b-55c25fe0cea7"},"created_time":"2023-05-21T00:22:00.000Z","last_edited_time":"2023-05-21T00:22:00.000Z","created_by":{"object":"user","id":"f4f222d4-d508-405d-ba6c-da82ee26ee54"},"last_edited_by":{"object":"user","id":"f4f222d4-d508-405d-ba6c-da82ee26ee54"},"has_children":false,"archived":false,"in_trash":false,"type":"paragraph","paragraph":{"rich_text":[{"type":"text","text":{"content":"webpack.config.js:","link":null},"annotations":{"bold":false,"italic":false,"strikethrough":false,"underline":false,"code":false,"color":"default"},"plain_text":"webpack.config.js:","href":null}],"color":"default"}},{"object":"block","id":"08762e8c-7323-4a0f-86c8-db846f7750ee","parent":{"type":"page_id","page_id":"ba94cfed-9b64-41d3-862b-55c25fe0cea7"},"created_time":"2023-05-21T00:22:00.000Z","last_edited_time":"2023-05-21T01:33:00.000Z","created_by":{"object":"user","id":"f4f222d4-d508-405d-ba6c-da82ee26ee54"},"last_edited_by":{"object":"user","id":"f4f222d4-d508-405d-ba6c-da82ee26ee54"},"has_children":false,"archived":false,"in_trash":false,"type":"code","code":{"caption":[],"rich_text":[{"type":"text","text":{"content":"module.exports = () => {\n  return {\n    entry: {\n      main: \"./src/main.ts\"\n    },\n    output: {\n      path: \"./dist\",\n      filename: \"[name].bundle.js\"\n    },\n    resolve: {\n      extensions: [\".js\", \".ts\", \".html\"]\n    },\n    module: {\n      rules: [\n        {\n          test: /\\.ts$/,\n          loaders: [\"awesome-typescript-loader\", \"angular2-template-loader\"]\n        },\n        {\n          test: /\\.html$/,\n          loader: \"raw\"\n        }\n      ]\n    },\n    devtool: \"inline-source-map\"\n  };\n};","link":null},"annotations":{"bold":false,"italic":false,"strikethrough":false,"underline":false,"code":false,"color":"default"},"plain_text":"module.exports = () => {\n  return {\n    entry: {\n      main: \"./src/main.ts\"\n    },\n    output: {\n      path: \"./dist\",\n      filename: \"[name].bundle.js\"\n    },\n    resolve: {\n      extensions: [\".js\", \".ts\", \".html\"]\n    },\n    module: {\n      rules: [\n        {\n          test: /\\.ts$/,\n          loaders: [\"awesome-typescript-loader\", \"angular2-template-loader\"]\n        },\n        {\n          test: /\\.html$/,\n          loader: \"raw\"\n        }\n      ]\n    },\n    devtool: \"inline-source-map\"\n  };\n};","href":null}],"language":"plain text"}},{"object":"block","id":"039f1dec-ace9-4d28-9867-3d9d7abf0ae0","parent":{"type":"page_id","page_id":"ba94cfed-9b64-41d3-862b-55c25fe0cea7"},"created_time":"2023-05-21T00:22:00.000Z","last_edited_time":"2023-05-21T00:22:00.000Z","created_by":{"object":"user","id":"f4f222d4-d508-405d-ba6c-da82ee26ee54"},"last_edited_by":{"object":"user","id":"f4f222d4-d508-405d-ba6c-da82ee26ee54"},"has_children":false,"archived":false,"in_trash":false,"type":"paragraph","paragraph":{"rich_text":[{"type":"text","text":{"content":"package.json (scripts only):","link":null},"annotations":{"bold":false,"italic":false,"strikethrough":false,"underline":false,"code":false,"color":"default"},"plain_text":"package.json (scripts only):","href":null}],"color":"default"}},{"object":"block","id":"1ba0b697-718d-422d-98e9-51351d9c3394","parent":{"type":"page_id","page_id":"ba94cfed-9b64-41d3-862b-55c25fe0cea7"},"created_time":"2023-05-21T00:22:00.000Z","last_edited_time":"2023-05-21T01:34:00.000Z","created_by":{"object":"user","id":"f4f222d4-d508-405d-ba6c-da82ee26ee54"},"last_edited_by":{"object":"user","id":"f4f222d4-d508-405d-ba6c-da82ee26ee54"},"has_children":false,"archived":false,"in_trash":false,"type":"code","code":{"caption":[],"rich_text":[{"type":"text","text":{"content":"\"scripts\": {\n    \"build\": \"webpack\",\n    \"start\": \"static .\"\n},","link":null},"annotations":{"bold":false,"italic":false,"strikethrough":false,"underline":false,"code":false,"color":"default"},"plain_text":"\"scripts\": {\n    \"build\": \"webpack\",\n    \"start\": \"static .\"\n},","href":null}],"language":"json"}},{"object":"block","id":"dc0f9f13-940e-42b6-8f1d-a6ef0ae3351b","parent":{"type":"page_id","page_id":"ba94cfed-9b64-41d3-862b-55c25fe0cea7"},"created_time":"2023-05-21T00:22:00.000Z","last_edited_time":"2023-05-21T00:22:00.000Z","created_by":{"object":"user","id":"f4f222d4-d508-405d-ba6c-da82ee26ee54"},"last_edited_by":{"object":"user","id":"f4f222d4-d508-405d-ba6c-da82ee26ee54"},"has_children":false,"archived":false,"in_trash":false,"type":"paragraph","paragraph":{"rich_text":[{"type":"text","text":{"content":"Yay, We’ve created an awesome application quickly.","link":null},"annotations":{"bold":false,"italic":false,"strikethrough":false,"underline":false,"code":false,"color":"default"},"plain_text":"Yay, We’ve created an awesome application quickly.","href":null}],"color":"default"}},{"object":"block","id":"06bdd973-f485-44d4-bb10-13f8de353422","parent":{"type":"page_id","page_id":"ba94cfed-9b64-41d3-862b-55c25fe0cea7"},"created_time":"2023-05-21T00:22:00.000Z","last_edited_time":"2023-05-21T00:22:00.000Z","created_by":{"object":"user","id":"f4f222d4-d508-405d-ba6c-da82ee26ee54"},"last_edited_by":{"object":"user","id":"f4f222d4-d508-405d-ba6c-da82ee26ee54"},"has_children":false,"archived":false,"in_trash":false,"type":"heading_2","heading_2":{"rich_text":[{"type":"text","text":{"content":"Setting up Karma runner","link":null},"annotations":{"bold":false,"italic":false,"strikethrough":false,"underline":false,"code":false,"color":"default"},"plain_text":"Setting up Karma runner","href":null}],"is_toggleable":false,"color":"default"}},{"object":"block","id":"7a154a48-ffbc-4adc-9613-19fd0967191a","parent":{"type":"page_id","page_id":"ba94cfed-9b64-41d3-862b-55c25fe0cea7"},"created_time":"2023-05-21T00:22:00.000Z","last_edited_time":"2023-05-21T00:22:00.000Z","created_by":{"object":"user","id":"f4f222d4-d508-405d-ba6c-da82ee26ee54"},"last_edited_by":{"object":"user","id":"f4f222d4-d508-405d-ba6c-da82ee26ee54"},"has_children":false,"archived":false,"in_trash":false,"type":"paragraph","paragraph":{"rich_text":[{"type":"text","text":{"content":"To make testing environment, we have to set up Karma test runner at first. Follow the command below:","link":null},"annotations":{"bold":false,"italic":false,"strikethrough":false,"underline":false,"code":false,"color":"default"},"plain_text":"To make testing environment, we have to set up Karma test runner at first. Follow the command below:","href":null}],"color":"default"}},{"object":"block","id":"6980b67a-105f-422f-9062-ea28033cc79a","parent":{"type":"page_id","page_id":"ba94cfed-9b64-41d3-862b-55c25fe0cea7"},"created_time":"2023-05-21T00:22:00.000Z","last_edited_time":"2023-05-21T00:22:00.000Z","created_by":{"object":"user","id":"f4f222d4-d508-405d-ba6c-da82ee26ee54"},"last_edited_by":{"object":"user","id":"f4f222d4-d508-405d-ba6c-da82ee26ee54"},"has_children":false,"archived":false,"in_trash":false,"type":"code","code":{"caption":[],"rich_text":[{"type":"text","text":{"content":"> npm i -D karma jasmine\n> $(npm bin)/karma init","link":null},"annotations":{"bold":false,"italic":false,"strikethrough":false,"underline":false,"code":false,"color":"default"},"plain_text":"> npm i -D karma jasmine\n> $(npm bin)/karma init","href":null}],"language":"plain text"}},{"object":"block","id":"b09479df-acc4-463e-915d-21ffc64512fb","parent":{"type":"page_id","page_id":"ba94cfed-9b64-41d3-862b-55c25fe0cea7"},"created_time":"2023-05-21T00:22:00.000Z","last_edited_time":"2023-05-21T00:22:00.000Z","created_by":{"object":"user","id":"f4f222d4-d508-405d-ba6c-da82ee26ee54"},"last_edited_by":{"object":"user","id":"f4f222d4-d508-405d-ba6c-da82ee26ee54"},"has_children":false,"archived":false,"in_trash":false,"type":"paragraph","paragraph":{"rich_text":[{"type":"text","text":{"content":"This is the starting point of karma.config.js","link":null},"annotations":{"bold":false,"italic":false,"strikethrough":false,"underline":false,"code":false,"color":"default"},"plain_text":"This is the starting point of karma.config.js","href":null}],"color":"default"}},{"object":"block","id":"507dd755-b40b-4fb7-843b-92e7f872e7ce","parent":{"type":"page_id","page_id":"ba94cfed-9b64-41d3-862b-55c25fe0cea7"},"created_time":"2023-05-21T00:22:00.000Z","last_edited_time":"2023-05-21T01:34:00.000Z","created_by":{"object":"user","id":"f4f222d4-d508-405d-ba6c-da82ee26ee54"},"last_edited_by":{"object":"user","id":"f4f222d4-d508-405d-ba6c-da82ee26ee54"},"has_children":false,"archived":false,"in_trash":false,"type":"code","code":{"caption":[],"rich_text":[{"type":"text","text":{"content":"module.exports = function(config) {\n  config.set({\n    basePath: \"\",\n    frameworks: [\"jasmine\"],\n    files: [],\n    exclude: [],\n    preprocessors: {},\n    reporters: [\"progress\"],\n    port: 9876,\n    colors: true,\n    logLevel: config.LOG_INFO,\n    autoWatch: false,\n    browsers: [\"Chrome\"],\n    singleRun: true,\n    concurrency: Infinity\n  });\n};","link":null},"annotations":{"bold":false,"italic":false,"strikethrough":false,"underline":false,"code":false,"color":"default"},"plain_text":"module.exports = function(config) {\n  config.set({\n    basePath: \"\",\n    frameworks: [\"jasmine\"],\n    files: [],\n    exclude: [],\n    preprocessors: {},\n    reporters: [\"progress\"],\n    port: 9876,\n    colors: true,\n    logLevel: config.LOG_INFO,\n    autoWatch: false,\n    browsers: [\"Chrome\"],\n    singleRun: true,\n    concurrency: Infinity\n  });\n};","href":null}],"language":"plain text"}},{"object":"block","id":"023041c1-0c08-4b23-a5c4-682c701ebad8","parent":{"type":"page_id","page_id":"ba94cfed-9b64-41d3-862b-55c25fe0cea7"},"created_time":"2023-05-21T00:22:00.000Z","last_edited_time":"2023-05-21T00:22:00.000Z","created_by":{"object":"user","id":"f4f222d4-d508-405d-ba6c-da82ee26ee54"},"last_edited_by":{"object":"user","id":"f4f222d4-d508-405d-ba6c-da82ee26ee54"},"has_children":false,"archived":false,"in_trash":false,"type":"heading_2","heading_2":{"rich_text":[{"type":"text","text":{"content":"Add test file","link":null},"annotations":{"bold":false,"italic":false,"strikethrough":false,"underline":false,"code":false,"color":"default"},"plain_text":"Add test file","href":null}],"is_toggleable":false,"color":"default"}},{"object":"block","id":"497b070d-88b6-4dc8-b4a3-72e7253314f9","parent":{"type":"page_id","page_id":"ba94cfed-9b64-41d3-862b-55c25fe0cea7"},"created_time":"2023-05-21T00:22:00.000Z","last_edited_time":"2023-05-21T00:22:00.000Z","created_by":{"object":"user","id":"f4f222d4-d508-405d-ba6c-da82ee26ee54"},"last_edited_by":{"object":"user","id":"f4f222d4-d508-405d-ba6c-da82ee26ee54"},"has_children":false,"archived":false,"in_trash":false,"type":"paragraph","paragraph":{"rich_text":[{"type":"text","text":{"content":"First step, let’s make a test file and add it into karma runner. Create test/main.js as following:","link":null},"annotations":{"bold":false,"italic":false,"strikethrough":false,"underline":false,"code":false,"color":"default"},"plain_text":"First step, let’s make a test file and add it into karma runner. Create test/main.js as following:","href":null}],"color":"default"}},{"object":"block","id":"8f13f5d5-c85b-46f5-a42a-0f645d6aa6e3","parent":{"type":"page_id","page_id":"ba94cfed-9b64-41d3-862b-55c25fe0cea7"},"created_time":"2023-05-21T00:22:00.000Z","last_edited_time":"2023-05-21T01:34:00.000Z","created_by":{"object":"user","id":"f4f222d4-d508-405d-ba6c-da82ee26ee54"},"last_edited_by":{"object":"user","id":"f4f222d4-d508-405d-ba6c-da82ee26ee54"},"has_children":false,"archived":false,"in_trash":false,"type":"code","code":{"caption":[],"rich_text":[{"type":"text","text":{"content":"describe(\"Meaningful Test\", () => {\n  it(\"1 + 1 => 2\", () => {\n    expect(1 + 1).toBe(2);\n  });\n});","link":null},"annotations":{"bold":false,"italic":false,"strikethrough":false,"underline":false,"code":false,"color":"default"},"plain_text":"describe(\"Meaningful Test\", () => {\n  it(\"1 + 1 => 2\", () => {\n    expect(1 + 1).toBe(2);\n  });\n});","href":null}],"language":"plain text"}},{"object":"block","id":"71427c95-c264-4038-98a8-238e4a713e01","parent":{"type":"page_id","page_id":"ba94cfed-9b64-41d3-862b-55c25fe0cea7"},"created_time":"2023-05-21T00:22:00.000Z","last_edited_time":"2023-05-21T00:22:00.000Z","created_by":{"object":"user","id":"f4f222d4-d508-405d-ba6c-da82ee26ee54"},"last_edited_by":{"object":"user","id":"f4f222d4-d508-405d-ba6c-da82ee26ee54"},"has_children":false,"archived":false,"in_trash":false,"type":"paragraph","paragraph":{"rich_text":[{"type":"text","text":{"content":"And update files property in karma configuration:","link":null},"annotations":{"bold":false,"italic":false,"strikethrough":false,"underline":false,"code":false,"color":"default"},"plain_text":"And update files property in karma configuration:","href":null}],"color":"default"}},{"object":"block","id":"20a0e6e8-8f21-44a4-aa9f-0d63f1569f92","parent":{"type":"page_id","page_id":"ba94cfed-9b64-41d3-862b-55c25fe0cea7"},"created_time":"2023-05-21T00:22:00.000Z","last_edited_time":"2023-05-21T01:34:00.000Z","created_by":{"object":"user","id":"f4f222d4-d508-405d-ba6c-da82ee26ee54"},"last_edited_by":{"object":"user","id":"f4f222d4-d508-405d-ba6c-da82ee26ee54"},"has_children":false,"archived":false,"in_trash":false,"type":"code","code":{"caption":[],"rich_text":[{"type":"text","text":{"content":"files: [\n  { pattern: 'test/main.js' }\n],","link":null},"annotations":{"bold":false,"italic":false,"strikethrough":false,"underline":false,"code":false,"color":"default"},"plain_text":"files: [\n  { pattern: 'test/main.js' }\n],","href":null}],"language":"plain text"}},{"object":"block","id":"f1277dbc-d603-4fa5-803f-891a6f119fe2","parent":{"type":"page_id","page_id":"ba94cfed-9b64-41d3-862b-55c25fe0cea7"},"created_time":"2023-05-21T00:22:00.000Z","last_edited_time":"2023-05-21T00:22:00.000Z","created_by":{"object":"user","id":"f4f222d4-d508-405d-ba6c-da82ee26ee54"},"last_edited_by":{"object":"user","id":"f4f222d4-d508-405d-ba6c-da82ee26ee54"},"has_children":false,"archived":false,"in_trash":false,"type":"paragraph","paragraph":{"rich_text":[{"type":"text","text":{"content":"At last, add “test” npm-script in package.json:","link":null},"annotations":{"bold":false,"italic":false,"strikethrough":false,"underline":false,"code":false,"color":"default"},"plain_text":"At last, add “test” npm-script in package.json:","href":null}],"color":"default"}},{"object":"block","id":"c1b87e83-9920-45bf-b65a-cd4e4e445e5d","parent":{"type":"page_id","page_id":"ba94cfed-9b64-41d3-862b-55c25fe0cea7"},"created_time":"2023-05-21T00:22:00.000Z","last_edited_time":"2023-05-21T01:34:00.000Z","created_by":{"object":"user","id":"f4f222d4-d508-405d-ba6c-da82ee26ee54"},"last_edited_by":{"object":"user","id":"f4f222d4-d508-405d-ba6c-da82ee26ee54"},"has_children":false,"archived":false,"in_trash":false,"type":"code","code":{"caption":[],"rich_text":[{"type":"text","text":{"content":"\"scripts\": {\n    \"build\": \"webpack\",\n    \"start\": \"static .\",\n    \"test\": \"karma start\"\n},","link":null},"annotations":{"bold":false,"italic":false,"strikethrough":false,"underline":false,"code":false,"color":"default"},"plain_text":"\"scripts\": {\n    \"build\": \"webpack\",\n    \"start\": \"static .\",\n    \"test\": \"karma start\"\n},","href":null}],"language":"json"}},{"object":"block","id":"af4e647f-71ae-4b7b-ac72-0dd75afa6b1f","parent":{"type":"page_id","page_id":"ba94cfed-9b64-41d3-862b-55c25fe0cea7"},"created_time":"2023-05-21T00:22:00.000Z","last_edited_time":"2023-05-21T01:35:00.000Z","created_by":{"object":"user","id":"f4f222d4-d508-405d-ba6c-da82ee26ee54"},"last_edited_by":{"object":"user","id":"f4f222d4-d508-405d-ba6c-da82ee26ee54"},"has_children":false,"archived":false,"in_trash":false,"type":"paragraph","paragraph":{"rich_text":[{"type":"text","text":{"content":"Let’s execute “npm test” command.","link":null},"annotations":{"bold":false,"italic":false,"strikethrough":false,"underline":false,"code":false,"color":"default"},"plain_text":"Let’s execute “npm test” command.","href":null}],"color":"default"}},{"object":"block","id":"d5b20699-e047-43f7-9e21-3f7521a56027","parent":{"type":"page_id","page_id":"ba94cfed-9b64-41d3-862b-55c25fe0cea7"},"created_time":"2023-05-21T00:22:00.000Z","last_edited_time":"2023-05-21T01:35:00.000Z","created_by":{"object":"user","id":"f4f222d4-d508-405d-ba6c-da82ee26ee54"},"last_edited_by":{"object":"user","id":"f4f222d4-d508-405d-ba6c-da82ee26ee54"},"has_children":false,"archived":false,"in_trash":false,"type":"image","image":{"caption":[],"type":"file","file":{"url":"https://prod-files-secure.s3.us-west-2.amazonaws.com/3c6255ea-b6c7-4055-8126-638d2819f0c3/1af5e44e-a7af-45d5-abcb-db96dd153fed/npm_test.png?X-Amz-Algorithm=AWS4-HMAC-SHA256&X-Amz-Content-Sha256=UNSIGNED-PAYLOAD&X-Amz-Credential=AKIAT73L2G45HZZMZUHI%2F20240710%2Fus-west-2%2Fs3%2Faws4_request&X-Amz-Date=20240710T093635Z&X-Amz-Expires=3600&X-Amz-Signature=fe687125e7f555e558432d764d28d8a231e1dea1a3fa919404c02a786674fd10&X-Amz-SignedHeaders=host&x-id=GetObject","expiry_time":"2024-07-10T10:36:35.338Z"}}},{"object":"block","id":"c5997e82-5c68-4669-b495-727f18c17da9","parent":{"type":"page_id","page_id":"ba94cfed-9b64-41d3-862b-55c25fe0cea7"},"created_time":"2023-05-21T00:22:00.000Z","last_edited_time":"2023-05-21T00:22:00.000Z","created_by":{"object":"user","id":"f4f222d4-d508-405d-ba6c-da82ee26ee54"},"last_edited_by":{"object":"user","id":"f4f222d4-d508-405d-ba6c-da82ee26ee54"},"has_children":false,"archived":false,"in_trash":false,"type":"paragraph","paragraph":{"rich_text":[{"type":"text","text":{"content":"Okey! Setting up karma runner is done! Let’s go to next step.","link":null},"annotations":{"bold":false,"italic":false,"strikethrough":false,"underline":false,"code":false,"color":"default"},"plain_text":"Okey! Setting up karma runner is done! Let’s go to next step.","href":null}],"color":"default"}},{"object":"block","id":"8831bb24-0613-4b30-8127-69d28142d022","parent":{"type":"page_id","page_id":"ba94cfed-9b64-41d3-862b-55c25fe0cea7"},"created_time":"2023-05-21T00:22:00.000Z","last_edited_time":"2023-05-21T00:22:00.000Z","created_by":{"object":"user","id":"f4f222d4-d508-405d-ba6c-da82ee26ee54"},"last_edited_by":{"object":"user","id":"f4f222d4-d508-405d-ba6c-da82ee26ee54"},"has_children":false,"archived":false,"in_trash":false,"type":"heading_2","heading_2":{"rich_text":[{"type":"text","text":{"content":"Use modules and karma-webpack","link":null},"annotations":{"bold":false,"italic":false,"strikethrough":false,"underline":false,"code":false,"color":"default"},"plain_text":"Use modules and karma-webpack","href":null}],"is_toggleable":false,"color":"default"}},{"object":"block","id":"d0ad919d-4e78-4462-97ee-53822b3b64cf","parent":{"type":"page_id","page_id":"ba94cfed-9b64-41d3-862b-55c25fe0cea7"},"created_time":"2023-05-21T00:22:00.000Z","last_edited_time":"2023-05-21T00:22:00.000Z","created_by":{"object":"user","id":"f4f222d4-d508-405d-ba6c-da82ee26ee54"},"last_edited_by":{"object":"user","id":"f4f222d4-d508-405d-ba6c-da82ee26ee54"},"has_children":false,"archived":false,"in_trash":false,"type":"paragraph","paragraph":{"rich_text":[{"type":"text","text":{"content":"Now, our test is only one file. So after now, all tests have to be written in test/main.js or add new file into karma configuration every times… Really?","link":null},"annotations":{"bold":false,"italic":false,"strikethrough":false,"underline":false,"code":false,"color":"default"},"plain_text":"Now, our test is only one file. So after now, all tests have to be written in test/main.js or add new file into karma configuration every times… Really?","href":null}],"color":"default"}},{"object":"block","id":"ee7e4f74-869d-4dcc-8544-04aafbc9f775","parent":{"type":"page_id","page_id":"ba94cfed-9b64-41d3-862b-55c25fe0cea7"},"created_time":"2023-05-21T00:22:00.000Z","last_edited_time":"2023-05-21T00:22:00.000Z","created_by":{"object":"user","id":"f4f222d4-d508-405d-ba6c-da82ee26ee54"},"last_edited_by":{"object":"user","id":"f4f222d4-d508-405d-ba6c-da82ee26ee54"},"has_children":false,"archived":false,"in_trash":false,"type":"paragraph","paragraph":{"rich_text":[{"type":"text","text":{"content":"No! Don’t worry, guys. We can separate tests as modules and bundle it to the single test file. No updates on karma configuration by per test.","link":null},"annotations":{"bold":false,"italic":false,"strikethrough":false,"underline":false,"code":false,"color":"default"},"plain_text":"No! Don’t worry, guys. We can separate tests as modules and bundle it to the single test file. No updates on karma configuration by per test.","href":null}],"color":"default"}},{"object":"block","id":"5982ee72-59ac-4333-b8b3-5ce4baf5e34f","parent":{"type":"page_id","page_id":"ba94cfed-9b64-41d3-862b-55c25fe0cea7"},"created_time":"2023-05-21T00:22:00.000Z","last_edited_time":"2023-05-21T00:22:00.000Z","created_by":{"object":"user","id":"f4f222d4-d508-405d-ba6c-da82ee26ee54"},"last_edited_by":{"object":"user","id":"f4f222d4-d508-405d-ba6c-da82ee26ee54"},"has_children":false,"archived":false,"in_trash":false,"type":"paragraph","paragraph":{"rich_text":[{"type":"text","text":{"content":"Let’s get it started. Install karma-webpack and karma-sourcemap-loader at first:","link":null},"annotations":{"bold":false,"italic":false,"strikethrough":false,"underline":false,"code":false,"color":"default"},"plain_text":"Let’s get it started. Install karma-webpack and karma-sourcemap-loader at first:","href":null}],"color":"default"}},{"object":"block","id":"fbc799ee-30cb-4558-a6ae-6991a772d555","parent":{"type":"page_id","page_id":"ba94cfed-9b64-41d3-862b-55c25fe0cea7"},"created_time":"2023-05-21T00:22:00.000Z","last_edited_time":"2023-05-21T00:22:00.000Z","created_by":{"object":"user","id":"f4f222d4-d508-405d-ba6c-da82ee26ee54"},"last_edited_by":{"object":"user","id":"f4f222d4-d508-405d-ba6c-da82ee26ee54"},"has_children":false,"archived":false,"in_trash":false,"type":"code","code":{"caption":[],"rich_text":[{"type":"text","text":{"content":"> npm i -D karma-webpack karma-sourcemap-loader","link":null},"annotations":{"bold":false,"italic":false,"strikethrough":false,"underline":false,"code":false,"color":"default"},"plain_text":"> npm i -D karma-webpack karma-sourcemap-loader","href":null}],"language":"plain text"}},{"object":"block","id":"d68c44d1-e7ea-4948-acf2-c9dae640d37a","parent":{"type":"page_id","page_id":"ba94cfed-9b64-41d3-862b-55c25fe0cea7"},"created_time":"2023-05-21T00:22:00.000Z","last_edited_time":"2023-05-21T00:22:00.000Z","created_by":{"object":"user","id":"f4f222d4-d508-405d-ba6c-da82ee26ee54"},"last_edited_by":{"object":"user","id":"f4f222d4-d508-405d-ba6c-da82ee26ee54"},"has_children":false,"archived":false,"in_trash":false,"type":"paragraph","paragraph":{"rich_text":[{"type":"text","text":{"content":"And then, update our karma.config.js. Look at ","link":null},"annotations":{"bold":false,"italic":false,"strikethrough":false,"underline":false,"code":false,"color":"default"},"plain_text":"And then, update our karma.config.js. Look at ","href":null},{"type":"text","text":{"content":"preprocessors","link":null},"annotations":{"bold":true,"italic":false,"strikethrough":false,"underline":false,"code":false,"color":"default"},"plain_text":"preprocessors","href":null},{"type":"text","text":{"content":" and ","link":null},"annotations":{"bold":false,"italic":false,"strikethrough":false,"underline":false,"code":false,"color":"default"},"plain_text":" and ","href":null},{"type":"text","text":{"content":"webpack","link":null},"annotations":{"bold":true,"italic":false,"strikethrough":false,"underline":false,"code":false,"color":"default"},"plain_text":"webpack","href":null},{"type":"text","text":{"content":" property. ","link":null},"annotations":{"bold":false,"italic":false,"strikethrough":false,"underline":false,"code":false,"color":"default"},"plain_text":" property. ","href":null},{"type":"text","text":{"content":"webpack","link":null},"annotations":{"bold":false,"italic":false,"strikethrough":false,"underline":false,"code":true,"color":"default"},"plain_text":"webpack","href":null},{"type":"text","text":{"content":" preprocessor executes webpack bundling using ","link":null},"annotations":{"bold":false,"italic":false,"strikethrough":false,"underline":false,"code":false,"color":"default"},"plain_text":" preprocessor executes webpack bundling using ","href":null},{"type":"text","text":{"content":"test/main.js","link":null},"annotations":{"bold":false,"italic":false,"strikethrough":false,"underline":false,"code":true,"color":"default"},"plain_text":"test/main.js","href":null},{"type":"text","text":{"content":" as an entry point. And ","link":null},"annotations":{"bold":false,"italic":false,"strikethrough":false,"underline":false,"code":false,"color":"default"},"plain_text":" as an entry point. And ","href":null},{"type":"text","text":{"content":"webpack","link":null},"annotations":{"bold":false,"italic":false,"strikethrough":false,"underline":false,"code":true,"color":"default"},"plain_text":"webpack","href":null},{"type":"text","text":{"content":" property is an configuration for the bundling.","link":null},"annotations":{"bold":false,"italic":false,"strikethrough":false,"underline":false,"code":false,"color":"default"},"plain_text":" property is an configuration for the bundling.","href":null}],"color":"default"}},{"object":"block","id":"b35635fb-8205-41c9-b2b6-a6850f1f1440","parent":{"type":"page_id","page_id":"ba94cfed-9b64-41d3-862b-55c25fe0cea7"},"created_time":"2023-05-21T00:22:00.000Z","last_edited_time":"2023-05-21T01:35:00.000Z","created_by":{"object":"user","id":"f4f222d4-d508-405d-ba6c-da82ee26ee54"},"last_edited_by":{"object":"user","id":"f4f222d4-d508-405d-ba6c-da82ee26ee54"},"has_children":false,"archived":false,"in_trash":false,"type":"code","code":{"caption":[],"rich_text":[{"type":"text","text":{"content":"module.exports = function(config) {\n  config.set({\n    basePath: \"\",\n    frameworks: [\"jasmine\"],\n    files: [{ pattern: \"test/main.js\", watched: false }],\n    exclude: [],\n    preprocessors: {\n      \"test/main.js\": [\"webpack\"]\n    },\n    webpack: require(\"./webpack.config\")({ env: \"test\" }),\n    reporters: [\"progress\"],\n    port: 9876,\n    colors: true,\n    logLevel: config.LOG_INFO,\n    autoWatch: false,\n    browsers: [\"Chrome\"],\n    singleRun: true,\n    concurrency: Infinity\n  });\n};","link":null},"annotations":{"bold":false,"italic":false,"strikethrough":false,"underline":false,"code":false,"color":"default"},"plain_text":"module.exports = function(config) {\n  config.set({\n    basePath: \"\",\n    frameworks: [\"jasmine\"],\n    files: [{ pattern: \"test/main.js\", watched: false }],\n    exclude: [],\n    preprocessors: {\n      \"test/main.js\": [\"webpack\"]\n    },\n    webpack: require(\"./webpack.config\")({ env: \"test\" }),\n    reporters: [\"progress\"],\n    port: 9876,\n    colors: true,\n    logLevel: config.LOG_INFO,\n    autoWatch: false,\n    browsers: [\"Chrome\"],\n    singleRun: true,\n    concurrency: Infinity\n  });\n};","href":null}],"language":"plain text"}},{"object":"block","id":"958b597b-5349-49d1-b5da-9966130a4e27","parent":{"type":"page_id","page_id":"ba94cfed-9b64-41d3-862b-55c25fe0cea7"},"created_time":"2023-05-21T00:22:00.000Z","last_edited_time":"2023-05-21T00:22:00.000Z","created_by":{"object":"user","id":"f4f222d4-d508-405d-ba6c-da82ee26ee54"},"last_edited_by":{"object":"user","id":"f4f222d4-d508-405d-ba6c-da82ee26ee54"},"has_children":false,"archived":false,"in_trash":false,"type":"paragraph","paragraph":{"rich_text":[{"type":"text","text":{"content":"Execute “npm test” again and see logs.","link":null},"annotations":{"bold":false,"italic":false,"strikethrough":false,"underline":false,"code":false,"color":"default"},"plain_text":"Execute “npm test” again and see logs.","href":null}],"color":"default"}},{"object":"block","id":"48af23d0-78d0-4cb0-b13f-195c5033e437","parent":{"type":"page_id","page_id":"ba94cfed-9b64-41d3-862b-55c25fe0cea7"},"created_time":"2023-05-21T00:22:00.000Z","last_edited_time":"2023-05-21T00:22:00.000Z","created_by":{"object":"user","id":"f4f222d4-d508-405d-ba6c-da82ee26ee54"},"last_edited_by":{"object":"user","id":"f4f222d4-d508-405d-ba6c-da82ee26ee54"},"has_children":false,"archived":false,"in_trash":false,"type":"code","code":{"caption":[],"rich_text":[{"type":"text","text":{"content":"> karma start\nwebpack: wait until bundle finished:\nHash: 1130517a944241558f1f\nVersion: webpack 2.1.0-beta.25\nTime: 3069ms\nAsset     Size  Chunks             Chunk Names\nmain  2.19 MB       0  [emitted]  main\ntest/main.js  6.55 kB       1  [emitted]  test/main.js\nchunk    {0} main (main) 1.77 MB [entry] [rendered]\n[0] ./~/core-js/modules/_export.js 1.6 kB {0} [built]\n[1] ./~/@angular/core/index.js 355 bytes {0} [built]\n...","link":null},"annotations":{"bold":false,"italic":false,"strikethrough":false,"underline":false,"code":false,"color":"default"},"plain_text":"> karma start\nwebpack: wait until bundle finished:\nHash: 1130517a944241558f1f\nVersion: webpack 2.1.0-beta.25\nTime: 3069ms\nAsset     Size  Chunks             Chunk Names\nmain  2.19 MB       0  [emitted]  main\ntest/main.js  6.55 kB       1  [emitted]  test/main.js\nchunk    {0} main (main) 1.77 MB [entry] [rendered]\n[0] ./~/core-js/modules/_export.js 1.6 kB {0} [built]\n[1] ./~/@angular/core/index.js 355 bytes {0} [built]\n...","href":null}],"language":"plain text"}},{"object":"block","id":"deeecd43-4934-4b98-91e8-1dff4423aa7e","parent":{"type":"page_id","page_id":"ba94cfed-9b64-41d3-862b-55c25fe0cea7"},"created_time":"2023-05-21T00:22:00.000Z","last_edited_time":"2023-05-21T00:22:00.000Z","created_by":{"object":"user","id":"f4f222d4-d508-405d-ba6c-da82ee26ee54"},"last_edited_by":{"object":"user","id":"f4f222d4-d508-405d-ba6c-da82ee26ee54"},"has_children":false,"archived":false,"in_trash":false,"type":"paragraph","paragraph":{"rich_text":[{"type":"text","text":{"content":"webpack runs! karma-webpack is a very easy way to integrate Karma and webpack. So now, let’s make the second test in ","link":null},"annotations":{"bold":false,"italic":false,"strikethrough":false,"underline":false,"code":false,"color":"default"},"plain_text":"webpack runs! karma-webpack is a very easy way to integrate Karma and webpack. So now, let’s make the second test in ","href":null},{"type":"text","text":{"content":"test/sub.js","link":null},"annotations":{"bold":true,"italic":false,"strikethrough":false,"underline":false,"code":false,"color":"default"},"plain_text":"test/sub.js","href":null},{"type":"text","text":{"content":":","link":null},"annotations":{"bold":false,"italic":false,"strikethrough":false,"underline":false,"code":false,"color":"default"},"plain_text":":","href":null}],"color":"default"}},{"object":"block","id":"5c2c6dbe-eeb2-4cc4-bf0b-84b3fa8459ad","parent":{"type":"page_id","page_id":"ba94cfed-9b64-41d3-862b-55c25fe0cea7"},"created_time":"2023-05-21T00:22:00.000Z","last_edited_time":"2023-05-21T01:35:00.000Z","created_by":{"object":"user","id":"f4f222d4-d508-405d-ba6c-da82ee26ee54"},"last_edited_by":{"object":"user","id":"f4f222d4-d508-405d-ba6c-da82ee26ee54"},"has_children":false,"archived":false,"in_trash":false,"type":"code","code":{"caption":[],"rich_text":[{"type":"text","text":{"content":"describe(\"sub test\", () => {\n  it(\"always fails\", () => {\n    expect(0).toBe(1);\n  });\n});","link":null},"annotations":{"bold":false,"italic":false,"strikethrough":false,"underline":false,"code":false,"color":"default"},"plain_text":"describe(\"sub test\", () => {\n  it(\"always fails\", () => {\n    expect(0).toBe(1);\n  });\n});","href":null}],"language":"plain text"}},{"object":"block","id":"3b6b2ac3-154b-44db-bf77-e374f21eca21","parent":{"type":"page_id","page_id":"ba94cfed-9b64-41d3-862b-55c25fe0cea7"},"created_time":"2023-05-21T00:22:00.000Z","last_edited_time":"2023-05-21T00:22:00.000Z","created_by":{"object":"user","id":"f4f222d4-d508-405d-ba6c-da82ee26ee54"},"last_edited_by":{"object":"user","id":"f4f222d4-d508-405d-ba6c-da82ee26ee54"},"has_children":false,"archived":false,"in_trash":false,"type":"paragraph","paragraph":{"rich_text":[{"type":"text","text":{"content":"And import that in test/main.js:","link":null},"annotations":{"bold":false,"italic":false,"strikethrough":false,"underline":false,"code":false,"color":"default"},"plain_text":"And import that in test/main.js:","href":null}],"color":"default"}},{"object":"block","id":"95f97233-aa84-47c8-a031-890053c4ca3f","parent":{"type":"page_id","page_id":"ba94cfed-9b64-41d3-862b-55c25fe0cea7"},"created_time":"2023-05-21T00:22:00.000Z","last_edited_time":"2023-05-21T01:35:00.000Z","created_by":{"object":"user","id":"f4f222d4-d508-405d-ba6c-da82ee26ee54"},"last_edited_by":{"object":"user","id":"f4f222d4-d508-405d-ba6c-da82ee26ee54"},"has_children":false,"archived":false,"in_trash":false,"type":"code","code":{"caption":[],"rich_text":[{"type":"text","text":{"content":"describe(\"Meaningful Test\", () => {\n  it(\"1 + 1 => 2\", () => {\n    expect(1 + 1).toBe(2);\n  });\n});\nimport \"./sub\";","link":null},"annotations":{"bold":false,"italic":false,"strikethrough":false,"underline":false,"code":false,"color":"default"},"plain_text":"describe(\"Meaningful Test\", () => {\n  it(\"1 + 1 => 2\", () => {\n    expect(1 + 1).toBe(2);\n  });\n});\nimport \"./sub\";","href":null}],"language":"plain text"}},{"object":"block","id":"631f2b6f-717e-4cd2-adaa-03a459b2c119","parent":{"type":"page_id","page_id":"ba94cfed-9b64-41d3-862b-55c25fe0cea7"},"created_time":"2023-05-21T00:22:00.000Z","last_edited_time":"2023-05-21T00:22:00.000Z","created_by":{"object":"user","id":"f4f222d4-d508-405d-ba6c-da82ee26ee54"},"last_edited_by":{"object":"user","id":"f4f222d4-d508-405d-ba6c-da82ee26ee54"},"has_children":false,"archived":false,"in_trash":false,"type":"paragraph","paragraph":{"rich_text":[{"type":"text","text":{"content":"test/sub.js contains the test fails always. In this state, try to run test once.","link":null},"annotations":{"bold":false,"italic":false,"strikethrough":false,"underline":false,"code":false,"color":"default"},"plain_text":"test/sub.js contains the test fails always. In this state, try to run test once.","href":null}],"color":"default"}},{"object":"block","id":"cd1b5d33-a788-4737-8636-2f9e97bd62f0","parent":{"type":"page_id","page_id":"ba94cfed-9b64-41d3-862b-55c25fe0cea7"},"created_time":"2023-05-21T00:22:00.000Z","last_edited_time":"2023-05-21T00:22:00.000Z","created_by":{"object":"user","id":"f4f222d4-d508-405d-ba6c-da82ee26ee54"},"last_edited_by":{"object":"user","id":"f4f222d4-d508-405d-ba6c-da82ee26ee54"},"has_children":false,"archived":false,"in_trash":false,"type":"code","code":{"caption":[],"rich_text":[{"type":"text","text":{"content":"Chrome 54.0.2840 (Mac OS X 10.11.6) sub test always fails FAILED\nExpected 0 to be 1.\nat Object.it (test/main.js:74:19)\nChrome 54.0.2840 (Mac OS X 10.11.6): Executed 2 of 2 (1 FAILED) (0.045 secs / 0.014 secs)","link":null},"annotations":{"bold":false,"italic":false,"strikethrough":false,"underline":false,"code":false,"color":"default"},"plain_text":"Chrome 54.0.2840 (Mac OS X 10.11.6) sub test always fails FAILED\nExpected 0 to be 1.\nat Object.it (test/main.js:74:19)\nChrome 54.0.2840 (Mac OS X 10.11.6): Executed 2 of 2 (1 FAILED) (0.045 secs / 0.014 secs)","href":null}],"language":"plain text"}},{"object":"block","id":"7c3945d5-1d1b-4e77-b60e-ceb9b97d4679","parent":{"type":"page_id","page_id":"ba94cfed-9b64-41d3-862b-55c25fe0cea7"},"created_time":"2023-05-21T00:22:00.000Z","last_edited_time":"2023-05-21T00:22:00.000Z","created_by":{"object":"user","id":"f4f222d4-d508-405d-ba6c-da82ee26ee54"},"last_edited_by":{"object":"user","id":"f4f222d4-d508-405d-ba6c-da82ee26ee54"},"has_children":false,"archived":false,"in_trash":false,"type":"paragraph","paragraph":{"rich_text":[{"type":"text","text":{"content":"As you can see, the test failed. It’s expected totally. But there is an important thing. Can you notice a weird information in that error logs?","link":null},"annotations":{"bold":false,"italic":false,"strikethrough":false,"underline":false,"code":false,"color":"default"},"plain_text":"As you can see, the test failed. It’s expected totally. But there is an important thing. Can you notice a weird information in that error logs?","href":null}],"color":"default"}},{"object":"block","id":"f77410b7-da3a-41fe-85b3-616eb14180e4","parent":{"type":"page_id","page_id":"ba94cfed-9b64-41d3-862b-55c25fe0cea7"},"created_time":"2023-05-21T00:22:00.000Z","last_edited_time":"2023-05-21T00:22:00.000Z","created_by":{"object":"user","id":"f4f222d4-d508-405d-ba6c-da82ee26ee54"},"last_edited_by":{"object":"user","id":"f4f222d4-d508-405d-ba6c-da82ee26ee54"},"has_children":false,"archived":false,"in_trash":false,"type":"paragraph","paragraph":{"rich_text":[{"type":"text","text":{"content":"Yes, it’s a stack trace. Despite we wrote failing test at test/sub.js, that error is logged as ","link":null},"annotations":{"bold":false,"italic":false,"strikethrough":false,"underline":false,"code":false,"color":"default"},"plain_text":"Yes, it’s a stack trace. Despite we wrote failing test at test/sub.js, that error is logged as ","href":null},{"type":"text","text":{"content":"at Object.it (test/main.js:74:19)","link":null},"annotations":{"bold":false,"italic":false,"strikethrough":false,"underline":false,"code":true,"color":"default"},"plain_text":"at Object.it (test/main.js:74:19)","href":null},{"type":"text","text":{"content":". It’s because of webpack bundling. That stack trace, ","link":null},"annotations":{"bold":false,"italic":false,"strikethrough":false,"underline":false,"code":false,"color":"default"},"plain_text":". It’s because of webpack bundling. That stack trace, ","href":null},{"type":"text","text":{"content":"(test/main.js:74:19)","link":null},"annotations":{"bold":false,"italic":false,"strikethrough":false,"underline":false,"code":true,"color":"default"},"plain_text":"(test/main.js:74:19)","href":null},{"type":"text","text":{"content":", points at the line of the bundled file. It needs ","link":null},"annotations":{"bold":false,"italic":false,"strikethrough":false,"underline":false,"code":false,"color":"default"},"plain_text":", points at the line of the bundled file. It needs ","href":null},{"type":"text","text":{"content":"sourcemap","link":null},"annotations":{"bold":true,"italic":false,"strikethrough":false,"underline":false,"code":false,"color":"default"},"plain_text":"sourcemap","href":null},{"type":"text","text":{"content":" information to show stack traces as we expect.","link":null},"annotations":{"bold":false,"italic":false,"strikethrough":false,"underline":false,"code":false,"color":"default"},"plain_text":" information to show stack traces as we expect.","href":null}],"color":"default"}},{"object":"block","id":"ba9b09f5-a9d5-475d-9888-afb4b38f5536","parent":{"type":"page_id","page_id":"ba94cfed-9b64-41d3-862b-55c25fe0cea7"},"created_time":"2023-05-21T00:22:00.000Z","last_edited_time":"2023-05-21T00:22:00.000Z","created_by":{"object":"user","id":"f4f222d4-d508-405d-ba6c-da82ee26ee54"},"last_edited_by":{"object":"user","id":"f4f222d4-d508-405d-ba6c-da82ee26ee54"},"has_children":false,"archived":false,"in_trash":false,"type":"paragraph","paragraph":{"rich_text":[{"type":"text","text":{"content":"Install ","link":null},"annotations":{"bold":false,"italic":false,"strikethrough":false,"underline":false,"code":false,"color":"default"},"plain_text":"Install ","href":null},{"type":"text","text":{"content":"karma-sourcemap-loader","link":null},"annotations":{"bold":true,"italic":false,"strikethrough":false,"underline":false,"code":false,"color":"default"},"plain_text":"karma-sourcemap-loader","href":null},{"type":"text","text":{"content":", which is a preprocessor for loading sourcemap into karma.","link":null},"annotations":{"bold":false,"italic":false,"strikethrough":false,"underline":false,"code":false,"color":"default"},"plain_text":", which is a preprocessor for loading sourcemap into karma.","href":null}],"color":"default"}},{"object":"block","id":"f5976d37-8138-4041-a9bc-3879ba34f586","parent":{"type":"page_id","page_id":"ba94cfed-9b64-41d3-862b-55c25fe0cea7"},"created_time":"2023-05-21T00:22:00.000Z","last_edited_time":"2023-05-21T00:22:00.000Z","created_by":{"object":"user","id":"f4f222d4-d508-405d-ba6c-da82ee26ee54"},"last_edited_by":{"object":"user","id":"f4f222d4-d508-405d-ba6c-da82ee26ee54"},"has_children":false,"archived":false,"in_trash":false,"type":"code","code":{"caption":[],"rich_text":[{"type":"text","text":{"content":"> npm i -D karma-sourcemap-loader","link":null},"annotations":{"bold":false,"italic":false,"strikethrough":false,"underline":false,"code":false,"color":"default"},"plain_text":"> npm i -D karma-sourcemap-loader","href":null}],"language":"plain text"}},{"object":"block","id":"84f55895-c60d-4033-8ad3-18001acea4c6","parent":{"type":"page_id","page_id":"ba94cfed-9b64-41d3-862b-55c25fe0cea7"},"created_time":"2023-05-21T00:22:00.000Z","last_edited_time":"2023-05-21T00:22:00.000Z","created_by":{"object":"user","id":"f4f222d4-d508-405d-ba6c-da82ee26ee54"},"last_edited_by":{"object":"user","id":"f4f222d4-d508-405d-ba6c-da82ee26ee54"},"has_children":false,"archived":false,"in_trash":false,"type":"paragraph","paragraph":{"rich_text":[{"type":"text","text":{"content":"Next, update karma.config.js to add “sourcemap” into preprocessors.","link":null},"annotations":{"bold":false,"italic":false,"strikethrough":false,"underline":false,"code":false,"color":"default"},"plain_text":"Next, update karma.config.js to add “sourcemap” into preprocessors.","href":null}],"color":"default"}},{"object":"block","id":"f9123e97-6bf8-4208-8b41-2abd7de5c3ce","parent":{"type":"page_id","page_id":"ba94cfed-9b64-41d3-862b-55c25fe0cea7"},"created_time":"2023-05-21T00:22:00.000Z","last_edited_time":"2023-05-21T01:35:00.000Z","created_by":{"object":"user","id":"f4f222d4-d508-405d-ba6c-da82ee26ee54"},"last_edited_by":{"object":"user","id":"f4f222d4-d508-405d-ba6c-da82ee26ee54"},"has_children":false,"archived":false,"in_trash":false,"type":"code","code":{"caption":[],"rich_text":[{"type":"text","text":{"content":"preprocessors: {\n    'test/main.js': ['webpack', 'sourcemap']\n},","link":null},"annotations":{"bold":false,"italic":false,"strikethrough":false,"underline":false,"code":false,"color":"default"},"plain_text":"preprocessors: {\n    'test/main.js': ['webpack', 'sourcemap']\n},","href":null}],"language":"plain text"}},{"object":"block","id":"f8813d74-4ef2-4dde-b852-4d645c6c7a71","parent":{"type":"page_id","page_id":"ba94cfed-9b64-41d3-862b-55c25fe0cea7"},"created_time":"2023-05-21T00:22:00.000Z","last_edited_time":"2023-05-21T00:22:00.000Z","created_by":{"object":"user","id":"f4f222d4-d508-405d-ba6c-da82ee26ee54"},"last_edited_by":{"object":"user","id":"f4f222d4-d508-405d-ba6c-da82ee26ee54"},"has_children":false,"archived":false,"in_trash":false,"type":"paragraph","paragraph":{"rich_text":[{"type":"text","text":{"content":"It’s ready! Let’s fail our test again and see error logs.","link":null},"annotations":{"bold":false,"italic":false,"strikethrough":false,"underline":false,"code":false,"color":"default"},"plain_text":"It’s ready! Let’s fail our test again and see error logs.","href":null}],"color":"default"}},{"object":"block","id":"9656cf5e-eb6e-40bb-9f83-72b3d3ccdc96","parent":{"type":"page_id","page_id":"ba94cfed-9b64-41d3-862b-55c25fe0cea7"},"created_time":"2023-05-21T00:22:00.000Z","last_edited_time":"2023-05-21T00:22:00.000Z","created_by":{"object":"user","id":"f4f222d4-d508-405d-ba6c-da82ee26ee54"},"last_edited_by":{"object":"user","id":"f4f222d4-d508-405d-ba6c-da82ee26ee54"},"has_children":false,"archived":false,"in_trash":false,"type":"code","code":{"caption":[],"rich_text":[{"type":"text","text":{"content":"Chrome 54.0.2840 (Mac OS X 10.11.6) sub test always fails FAILED\nExpected 0 to be 1.\nat Object.it (webpack:///test/sub.js:3:0 <- test/main.js:74:19)\nChrome 54.0.2840 (Mac OS X 10.11.6): Executed 2 of 2 (1 FAILED) (0.03 secs / 0.007 secs)","link":null},"annotations":{"bold":false,"italic":false,"strikethrough":false,"underline":false,"code":false,"color":"default"},"plain_text":"Chrome 54.0.2840 (Mac OS X 10.11.6) sub test always fails FAILED\nExpected 0 to be 1.\nat Object.it (webpack:///test/sub.js:3:0 <- test/main.js:74:19)\nChrome 54.0.2840 (Mac OS X 10.11.6): Executed 2 of 2 (1 FAILED) (0.03 secs / 0.007 secs)","href":null}],"language":"plain text"}},{"object":"block","id":"978e5ba3-412d-4fe1-9ee7-dbeb561f49fd","parent":{"type":"page_id","page_id":"ba94cfed-9b64-41d3-862b-55c25fe0cea7"},"created_time":"2023-05-21T00:22:00.000Z","last_edited_time":"2023-05-21T00:22:00.000Z","created_by":{"object":"user","id":"f4f222d4-d508-405d-ba6c-da82ee26ee54"},"last_edited_by":{"object":"user","id":"f4f222d4-d508-405d-ba6c-da82ee26ee54"},"has_children":false,"archived":false,"in_trash":false,"type":"paragraph","paragraph":{"rich_text":[{"type":"text","text":{"content":"Woohoo! That’s a perfect stack trace. We’ve got an environment to execute karma tests with webpack. But this is a starting point. Next step is setting up ","link":null},"annotations":{"bold":false,"italic":false,"strikethrough":false,"underline":false,"code":false,"color":"default"},"plain_text":"Woohoo! That’s a perfect stack trace. We’ve got an environment to execute karma tests with webpack. But this is a starting point. Next step is setting up ","href":null},{"type":"text","text":{"content":"Angular testing","link":null},"annotations":{"bold":true,"italic":false,"strikethrough":false,"underline":false,"code":false,"color":"default"},"plain_text":"Angular testing","href":null},{"type":"text","text":{"content":".","link":null},"annotations":{"bold":false,"italic":false,"strikethrough":false,"underline":false,"code":false,"color":"default"},"plain_text":".","href":null}],"color":"default"}},{"object":"block","id":"34d11d34-c1b9-4dd4-9d86-176673e88c23","parent":{"type":"page_id","page_id":"ba94cfed-9b64-41d3-862b-55c25fe0cea7"},"created_time":"2023-05-21T00:22:00.000Z","last_edited_time":"2023-05-21T00:22:00.000Z","created_by":{"object":"user","id":"f4f222d4-d508-405d-ba6c-da82ee26ee54"},"last_edited_by":{"object":"user","id":"f4f222d4-d508-405d-ba6c-da82ee26ee54"},"has_children":false,"archived":false,"in_trash":false,"type":"heading_2","heading_2":{"rich_text":[{"type":"text","text":{"content":"Setting up Angular Testing","link":null},"annotations":{"bold":false,"italic":false,"strikethrough":false,"underline":false,"code":false,"color":"default"},"plain_text":"Setting up Angular Testing","href":null}],"is_toggleable":false,"color":"default"}},{"object":"block","id":"e1f6b42b-4a8a-41eb-9cf8-731a22b344d6","parent":{"type":"page_id","page_id":"ba94cfed-9b64-41d3-862b-55c25fe0cea7"},"created_time":"2023-05-21T00:22:00.000Z","last_edited_time":"2023-05-21T00:22:00.000Z","created_by":{"object":"user","id":"f4f222d4-d508-405d-ba6c-da82ee26ee54"},"last_edited_by":{"object":"user","id":"f4f222d4-d508-405d-ba6c-da82ee26ee54"},"has_children":false,"archived":false,"in_trash":false,"type":"paragraph","paragraph":{"rich_text":[{"type":"text","text":{"content":"Currently we have the entry point for testing bundle but it’s a JavaScript file. Let’s create ","link":null},"annotations":{"bold":false,"italic":false,"strikethrough":false,"underline":false,"code":false,"color":"default"},"plain_text":"Currently we have the entry point for testing bundle but it’s a JavaScript file. Let’s create ","href":null},{"type":"text","text":{"content":"src/main.spec.ts","link":null},"annotations":{"bold":true,"italic":false,"strikethrough":false,"underline":false,"code":false,"color":"default"},"plain_text":"src/main.spec.ts","href":null},{"type":"text","text":{"content":" and update ","link":null},"annotations":{"bold":false,"italic":false,"strikethrough":false,"underline":false,"code":false,"color":"default"},"plain_text":" and update ","href":null},{"type":"text","text":{"content":"test/main.js","link":null},"annotations":{"bold":true,"italic":false,"strikethrough":false,"underline":false,"code":false,"color":"default"},"plain_text":"test/main.js","href":null},{"type":"text","text":{"content":" to import it. (no longer use test/sub.js).","link":null},"annotations":{"bold":false,"italic":false,"strikethrough":false,"underline":false,"code":false,"color":"default"},"plain_text":" to import it. (no longer use test/sub.js).","href":null}],"color":"default"}},{"object":"block","id":"98180d0b-16af-4dec-a3a8-e05af7e3d71a","parent":{"type":"page_id","page_id":"ba94cfed-9b64-41d3-862b-55c25fe0cea7"},"created_time":"2023-05-21T00:22:00.000Z","last_edited_time":"2023-05-21T00:22:00.000Z","created_by":{"object":"user","id":"f4f222d4-d508-405d-ba6c-da82ee26ee54"},"last_edited_by":{"object":"user","id":"f4f222d4-d508-405d-ba6c-da82ee26ee54"},"has_children":false,"archived":false,"in_trash":false,"type":"paragraph","paragraph":{"rich_text":[{"type":"text","text":{"content":"src/main.spec.ts:","link":null},"annotations":{"bold":false,"italic":false,"strikethrough":false,"underline":false,"code":false,"color":"default"},"plain_text":"src/main.spec.ts:","href":null}],"color":"default"}},{"object":"block","id":"f070bcd4-4146-4b62-9473-0e2783f088cc","parent":{"type":"page_id","page_id":"ba94cfed-9b64-41d3-862b-55c25fe0cea7"},"created_time":"2023-05-21T00:22:00.000Z","last_edited_time":"2023-05-21T01:36:00.000Z","created_by":{"object":"user","id":"f4f222d4-d508-405d-ba6c-da82ee26ee54"},"last_edited_by":{"object":"user","id":"f4f222d4-d508-405d-ba6c-da82ee26ee54"},"has_children":false,"archived":false,"in_trash":false,"type":"code","code":{"caption":[],"rich_text":[{"type":"text","text":{"content":"describe(\"main test\", () => {\n  it(\"always fails\", () => {\n    expect(0).toBe(1);\n  });\n});","link":null},"annotations":{"bold":false,"italic":false,"strikethrough":false,"underline":false,"code":false,"color":"default"},"plain_text":"describe(\"main test\", () => {\n  it(\"always fails\", () => {\n    expect(0).toBe(1);\n  });\n});","href":null}],"language":"plain text"}},{"object":"block","id":"6c784049-2387-4033-946e-890478458e5b","parent":{"type":"page_id","page_id":"ba94cfed-9b64-41d3-862b-55c25fe0cea7"},"created_time":"2023-05-21T00:22:00.000Z","last_edited_time":"2023-05-21T00:22:00.000Z","created_by":{"object":"user","id":"f4f222d4-d508-405d-ba6c-da82ee26ee54"},"last_edited_by":{"object":"user","id":"f4f222d4-d508-405d-ba6c-da82ee26ee54"},"has_children":false,"archived":false,"in_trash":false,"type":"paragraph","paragraph":{"rich_text":[{"type":"text","text":{"content":"test/main.js:","link":null},"annotations":{"bold":false,"italic":false,"strikethrough":false,"underline":false,"code":false,"color":"default"},"plain_text":"test/main.js:","href":null}],"color":"default"}},{"object":"block","id":"13d35f65-d8ff-43a1-a62c-a0c4e95191d8","parent":{"type":"page_id","page_id":"ba94cfed-9b64-41d3-862b-55c25fe0cea7"},"created_time":"2023-05-21T00:22:00.000Z","last_edited_time":"2023-05-21T00:22:00.000Z","created_by":{"object":"user","id":"f4f222d4-d508-405d-ba6c-da82ee26ee54"},"last_edited_by":{"object":"user","id":"f4f222d4-d508-405d-ba6c-da82ee26ee54"},"has_children":false,"archived":false,"in_trash":false,"type":"code","code":{"caption":[],"rich_text":[{"type":"text","text":{"content":"require(\"../src/main.spec.ts\");","link":null},"annotations":{"bold":false,"italic":false,"strikethrough":false,"underline":false,"code":false,"color":"default"},"plain_text":"require(\"../src/main.spec.ts\");","href":null}],"language":"plain text"}},{"object":"block","id":"6473daaa-3e36-40dd-8842-4c8383e5f313","parent":{"type":"page_id","page_id":"ba94cfed-9b64-41d3-862b-55c25fe0cea7"},"created_time":"2023-05-21T00:22:00.000Z","last_edited_time":"2023-05-21T00:22:00.000Z","created_by":{"object":"user","id":"f4f222d4-d508-405d-ba6c-da82ee26ee54"},"last_edited_by":{"object":"user","id":"f4f222d4-d508-405d-ba6c-da82ee26ee54"},"has_children":false,"archived":false,"in_trash":false,"type":"paragraph","paragraph":{"rich_text":[{"type":"text","text":{"content":"And install type definitions of Jasmine and add it into ","link":null},"annotations":{"bold":false,"italic":false,"strikethrough":false,"underline":false,"code":false,"color":"default"},"plain_text":"And install type definitions of Jasmine and add it into ","href":null},{"type":"text","text":{"content":"types","link":null},"annotations":{"bold":false,"italic":false,"strikethrough":false,"underline":false,"code":true,"color":"default"},"plain_text":"types","href":null},{"type":"text","text":{"content":" property of tsconfig.json.","link":null},"annotations":{"bold":false,"italic":false,"strikethrough":false,"underline":false,"code":false,"color":"default"},"plain_text":" property of tsconfig.json.","href":null}],"color":"default"}},{"object":"block","id":"ea9e297d-71fd-44ab-9266-be6df65c502b","parent":{"type":"page_id","page_id":"ba94cfed-9b64-41d3-862b-55c25fe0cea7"},"created_time":"2023-05-21T00:22:00.000Z","last_edited_time":"2023-05-21T00:22:00.000Z","created_by":{"object":"user","id":"f4f222d4-d508-405d-ba6c-da82ee26ee54"},"last_edited_by":{"object":"user","id":"f4f222d4-d508-405d-ba6c-da82ee26ee54"},"has_children":false,"archived":false,"in_trash":false,"type":"code","code":{"caption":[],"rich_text":[{"type":"text","text":{"content":"> npm i -D @types/jasmine","link":null},"annotations":{"bold":false,"italic":false,"strikethrough":false,"underline":false,"code":false,"color":"default"},"plain_text":"> npm i -D @types/jasmine","href":null}],"language":"plain text"}},{"object":"block","id":"1823952e-06b7-4d4c-83a9-84a18103ddd0","parent":{"type":"page_id","page_id":"ba94cfed-9b64-41d3-862b-55c25fe0cea7"},"created_time":"2023-05-21T00:22:00.000Z","last_edited_time":"2023-05-21T00:22:00.000Z","created_by":{"object":"user","id":"f4f222d4-d508-405d-ba6c-da82ee26ee54"},"last_edited_by":{"object":"user","id":"f4f222d4-d508-405d-ba6c-da82ee26ee54"},"has_children":false,"archived":false,"in_trash":false,"type":"paragraph","paragraph":{"rich_text":[{"type":"text","text":{"content":"tsconfig.json:","link":null},"annotations":{"bold":false,"italic":false,"strikethrough":false,"underline":false,"code":false,"color":"default"},"plain_text":"tsconfig.json:","href":null}],"color":"default"}},{"object":"block","id":"5f0a3d74-206a-4d32-ace4-c9ce51f3b3cc","parent":{"type":"page_id","page_id":"ba94cfed-9b64-41d3-862b-55c25fe0cea7"},"created_time":"2023-05-21T00:22:00.000Z","last_edited_time":"2023-05-21T01:36:00.000Z","created_by":{"object":"user","id":"f4f222d4-d508-405d-ba6c-da82ee26ee54"},"last_edited_by":{"object":"user","id":"f4f222d4-d508-405d-ba6c-da82ee26ee54"},"has_children":false,"archived":false,"in_trash":false,"type":"code","code":{"caption":[],"rich_text":[{"type":"text","text":{"content":"{\n  \"compilerOptions\": {\n    \"module\": \"es2015\",\n    \"target\": \"es5\",\n    \"noImplicitAny\": false,\n    \"sourceMap\": true,\n    \"moduleResolution\": \"node\",\n    \"experimentalDecorators\": true,\n    \"emitDecoratorMetadata\": true,\n    \"lib\": [\"es2015\", \"dom\"],\n    \"types\": [\"node\", \"jasmine\"]\n  },\n  \"awesomeTypeScriptLoaderOptions\": {\n    \"useWebpackText\": true\n  }\n}","link":null},"annotations":{"bold":false,"italic":false,"strikethrough":false,"underline":false,"code":false,"color":"default"},"plain_text":"{\n  \"compilerOptions\": {\n    \"module\": \"es2015\",\n    \"target\": \"es5\",\n    \"noImplicitAny\": false,\n    \"sourceMap\": true,\n    \"moduleResolution\": \"node\",\n    \"experimentalDecorators\": true,\n    \"emitDecoratorMetadata\": true,\n    \"lib\": [\"es2015\", \"dom\"],\n    \"types\": [\"node\", \"jasmine\"]\n  },\n  \"awesomeTypeScriptLoaderOptions\": {\n    \"useWebpackText\": true\n  }\n}","href":null}],"language":"json"}},{"object":"block","id":"e0392e76-bb20-476a-a11f-0163624f39fb","parent":{"type":"page_id","page_id":"ba94cfed-9b64-41d3-862b-55c25fe0cea7"},"created_time":"2023-05-21T00:22:00.000Z","last_edited_time":"2023-05-21T00:22:00.000Z","created_by":{"object":"user","id":"f4f222d4-d508-405d-ba6c-da82ee26ee54"},"last_edited_by":{"object":"user","id":"f4f222d4-d508-405d-ba6c-da82ee26ee54"},"has_children":false,"archived":false,"in_trash":false,"type":"paragraph","paragraph":{"rich_text":[{"type":"text","text":{"content":"Run tests. As below, sourcemap is working well even if tests are written in TypeScript.","link":null},"annotations":{"bold":false,"italic":false,"strikethrough":false,"underline":false,"code":false,"color":"default"},"plain_text":"Run tests. As below, sourcemap is working well even if tests are written in TypeScript.","href":null}],"color":"default"}},{"object":"block","id":"4cf610c4-fa31-4287-9db3-5fcd6b5a663c","parent":{"type":"page_id","page_id":"ba94cfed-9b64-41d3-862b-55c25fe0cea7"},"created_time":"2023-05-21T00:22:00.000Z","last_edited_time":"2023-05-21T00:22:00.000Z","created_by":{"object":"user","id":"f4f222d4-d508-405d-ba6c-da82ee26ee54"},"last_edited_by":{"object":"user","id":"f4f222d4-d508-405d-ba6c-da82ee26ee54"},"has_children":false,"archived":false,"in_trash":false,"type":"code","code":{"caption":[],"rich_text":[{"type":"text","text":{"content":"Chrome 54.0.2840 (Mac OS X 10.11.6) main test always fails FAILED\nExpected 0 to be 1.\nat Object.<anonymous> (webpack:///src/main.spec.ts:3:18 <- test/main.js:74:19)\nChrome 54.0.2840 (Mac OS X 10.11.6): Executed 1 of 1 (1 FAILED) ERROR (0.034 secs / 0.006 secs)","link":null},"annotations":{"bold":false,"italic":false,"strikethrough":false,"underline":false,"code":false,"color":"default"},"plain_text":"Chrome 54.0.2840 (Mac OS X 10.11.6) main test always fails FAILED\nExpected 0 to be 1.\nat Object.<anonymous> (webpack:///src/main.spec.ts:3:18 <- test/main.js:74:19)\nChrome 54.0.2840 (Mac OS X 10.11.6): Executed 1 of 1 (1 FAILED) ERROR (0.034 secs / 0.006 secs)","href":null}],"language":"plain text"}},{"object":"block","id":"7247ad3e-73fd-4bcd-8f30-4a33352e416d","parent":{"type":"page_id","page_id":"ba94cfed-9b64-41d3-862b-55c25fe0cea7"},"created_time":"2023-05-21T00:22:00.000Z","last_edited_time":"2023-05-21T00:22:00.000Z","created_by":{"object":"user","id":"f4f222d4-d508-405d-ba6c-da82ee26ee54"},"last_edited_by":{"object":"user","id":"f4f222d4-d508-405d-ba6c-da82ee26ee54"},"has_children":false,"archived":false,"in_trash":false,"type":"heading_2","heading_2":{"rich_text":[{"type":"text","text":{"content":"Initializing Angular TestBed","link":null},"annotations":{"bold":false,"italic":false,"strikethrough":false,"underline":false,"code":false,"color":"default"},"plain_text":"Initializing Angular TestBed","href":null}],"is_toggleable":false,"color":"default"}},{"object":"block","id":"2f260745-c507-4ee7-9cf3-bf4962a81d09","parent":{"type":"page_id","page_id":"ba94cfed-9b64-41d3-862b-55c25fe0cea7"},"created_time":"2023-05-21T00:22:00.000Z","last_edited_time":"2023-05-21T00:22:00.000Z","created_by":{"object":"user","id":"f4f222d4-d508-405d-ba6c-da82ee26ee54"},"last_edited_by":{"object":"user","id":"f4f222d4-d508-405d-ba6c-da82ee26ee54"},"has_children":false,"archived":false,"in_trash":false,"type":"paragraph","paragraph":{"rich_text":[{"type":"text","text":{"content":"Angular testing uses ","link":null},"annotations":{"bold":false,"italic":false,"strikethrough":false,"underline":false,"code":false,"color":"default"},"plain_text":"Angular testing uses ","href":null},{"type":"text","text":{"content":"TestBed","link":null},"annotations":{"bold":true,"italic":false,"strikethrough":false,"underline":false,"code":false,"color":"default"},"plain_text":"TestBed","href":null},{"type":"text","text":{"content":". We have to initialize it at the first of the test runner. In addition, importing ","link":null},"annotations":{"bold":false,"italic":false,"strikethrough":false,"underline":false,"code":false,"color":"default"},"plain_text":". We have to initialize it at the first of the test runner. In addition, importing ","href":null},{"type":"text","text":{"content":"polyfills","link":null},"annotations":{"bold":true,"italic":false,"strikethrough":false,"underline":false,"code":false,"color":"default"},"plain_text":"polyfills","href":null},{"type":"text","text":{"content":" and ","link":null},"annotations":{"bold":false,"italic":false,"strikethrough":false,"underline":false,"code":false,"color":"default"},"plain_text":" and ","href":null},{"type":"text","text":{"content":"zone.js","link":null},"annotations":{"bold":true,"italic":false,"strikethrough":false,"underline":false,"code":false,"color":"default"},"plain_text":"zone.js","href":null},{"type":"text","text":{"content":" is needed.","link":null},"annotations":{"bold":false,"italic":false,"strikethrough":false,"underline":false,"code":false,"color":"default"},"plain_text":" is needed.","href":null}],"color":"default"}},{"object":"block","id":"168fea39-a6a6-418f-a035-7c5560718e4a","parent":{"type":"page_id","page_id":"ba94cfed-9b64-41d3-862b-55c25fe0cea7"},"created_time":"2023-05-21T00:22:00.000Z","last_edited_time":"2023-05-21T00:22:00.000Z","created_by":{"object":"user","id":"f4f222d4-d508-405d-ba6c-da82ee26ee54"},"last_edited_by":{"object":"user","id":"f4f222d4-d508-405d-ba6c-da82ee26ee54"},"has_children":false,"archived":false,"in_trash":false,"type":"paragraph","paragraph":{"rich_text":[{"type":"text","text":{"content":"Update ","link":null},"annotations":{"bold":false,"italic":false,"strikethrough":false,"underline":false,"code":false,"color":"default"},"plain_text":"Update ","href":null},{"type":"text","text":{"content":"src/main.spec.ts","link":null},"annotations":{"bold":true,"italic":false,"strikethrough":false,"underline":false,"code":false,"color":"default"},"plain_text":"src/main.spec.ts","href":null},{"type":"text","text":{"content":" as following:","link":null},"annotations":{"bold":false,"italic":false,"strikethrough":false,"underline":false,"code":false,"color":"default"},"plain_text":" as following:","href":null}],"color":"default"}},{"object":"block","id":"789e1928-d238-4136-93e4-028b8692d1fd","parent":{"type":"page_id","page_id":"ba94cfed-9b64-41d3-862b-55c25fe0cea7"},"created_time":"2023-05-21T00:22:00.000Z","last_edited_time":"2023-05-21T01:36:00.000Z","created_by":{"object":"user","id":"f4f222d4-d508-405d-ba6c-da82ee26ee54"},"last_edited_by":{"object":"user","id":"f4f222d4-d508-405d-ba6c-da82ee26ee54"},"has_children":false,"archived":false,"in_trash":false,"type":"code","code":{"caption":[],"rich_text":[{"type":"text","text":{"content":"import \"core-js\"; // ES6 + reflect-metadata\n// zone.js\nimport \"zone.js/dist/zone\";\nimport \"zone.js/dist/proxy\";\nimport \"zone.js/dist/sync-test\";\nimport \"zone.js/dist/async-test\";\nimport \"zone.js/dist/jasmine-patch\";\n// TestBed initialization\nimport { TestBed } from \"@angular/core/testing\";\nimport {\n  BrowserDynamicTestingModule,\n  platformBrowserDynamicTesting\n} from \"@angular/platform-browser-dynamic/testing\";\nTestBed.initTestEnvironment(\n  BrowserDynamicTestingModule,\n  platformBrowserDynamicTesting()\n);","link":null},"annotations":{"bold":false,"italic":false,"strikethrough":false,"underline":false,"code":false,"color":"default"},"plain_text":"import \"core-js\"; // ES6 + reflect-metadata\n// zone.js\nimport \"zone.js/dist/zone\";\nimport \"zone.js/dist/proxy\";\nimport \"zone.js/dist/sync-test\";\nimport \"zone.js/dist/async-test\";\nimport \"zone.js/dist/jasmine-patch\";\n// TestBed initialization\nimport { TestBed } from \"@angular/core/testing\";\nimport {\n  BrowserDynamicTestingModule,\n  platformBrowserDynamicTesting\n} from \"@angular/platform-browser-dynamic/testing\";\nTestBed.initTestEnvironment(\n  BrowserDynamicTestingModule,\n  platformBrowserDynamicTesting()\n);","href":null}],"language":"plain text"}},{"object":"block","id":"7073442e-e645-4ac4-a3ea-549e1eb04a5b","parent":{"type":"page_id","page_id":"ba94cfed-9b64-41d3-862b-55c25fe0cea7"},"created_time":"2023-05-21T00:22:00.000Z","last_edited_time":"2023-05-21T01:36:00.000Z","created_by":{"object":"user","id":"f4f222d4-d508-405d-ba6c-da82ee26ee54"},"last_edited_by":{"object":"user","id":"f4f222d4-d508-405d-ba6c-da82ee26ee54"},"has_children":false,"archived":false,"in_trash":false,"type":"paragraph","paragraph":{"rich_text":[{"type":"text","text":{"content":"All preparing was completely ended! At the beginning, let’s make a pipe and its spec.","link":null},"annotations":{"bold":false,"italic":false,"strikethrough":false,"underline":false,"code":false,"color":"default"},"plain_text":"All preparing was completely ended! At the beginning, let’s make a pipe and its spec.","href":null}],"color":"default"}},{"object":"block","id":"94d7894b-4523-44c9-829d-29552ef7c6d9","parent":{"type":"page_id","page_id":"ba94cfed-9b64-41d3-862b-55c25fe0cea7"},"created_time":"2023-05-21T01:36:00.000Z","last_edited_time":"2023-05-21T01:36:00.000Z","created_by":{"object":"user","id":"f4f222d4-d508-405d-ba6c-da82ee26ee54"},"last_edited_by":{"object":"user","id":"f4f222d4-d508-405d-ba6c-da82ee26ee54"},"has_children":false,"archived":false,"in_trash":false,"type":"paragraph","paragraph":{"rich_text":[{"type":"text","text":{"content":"src/echo.pipe.ts;","link":null},"annotations":{"bold":false,"italic":false,"strikethrough":false,"underline":false,"code":false,"color":"default"},"plain_text":"src/echo.pipe.ts;","href":null}],"color":"default"}},{"object":"block","id":"53857f7b-0192-4d9f-9b24-51178e7bc6b1","parent":{"type":"page_id","page_id":"ba94cfed-9b64-41d3-862b-55c25fe0cea7"},"created_time":"2023-05-21T00:22:00.000Z","last_edited_time":"2023-05-21T01:36:00.000Z","created_by":{"object":"user","id":"f4f222d4-d508-405d-ba6c-da82ee26ee54"},"last_edited_by":{"object":"user","id":"f4f222d4-d508-405d-ba6c-da82ee26ee54"},"has_children":false,"archived":false,"in_trash":false,"type":"code","code":{"caption":[],"rich_text":[{"type":"text","text":{"content":"import { Pipe, PipeTransform } from \"@angular/core\";\n@Pipe({\n  name: \"echo\"\n})\nexport class EchoPipe implements PipeTransform {\n  transform(value: any): any {\n    return value;\n  }\n}","link":null},"annotations":{"bold":false,"italic":false,"strikethrough":false,"underline":false,"code":false,"color":"default"},"plain_text":"import { Pipe, PipeTransform } from \"@angular/core\";\n@Pipe({\n  name: \"echo\"\n})\nexport class EchoPipe implements PipeTransform {\n  transform(value: any): any {\n    return value;\n  }\n}","href":null}],"language":"plain text"}},{"object":"block","id":"0f098230-3b50-46a3-ae50-2d38725c6a13","parent":{"type":"page_id","page_id":"ba94cfed-9b64-41d3-862b-55c25fe0cea7"},"created_time":"2023-05-21T00:22:00.000Z","last_edited_time":"2023-05-21T00:22:00.000Z","created_by":{"object":"user","id":"f4f222d4-d508-405d-ba6c-da82ee26ee54"},"last_edited_by":{"object":"user","id":"f4f222d4-d508-405d-ba6c-da82ee26ee54"},"has_children":false,"archived":false,"in_trash":false,"type":"paragraph","paragraph":{"rich_text":[{"type":"text","text":{"content":"src/echo.pipe.spec.ts","link":null},"annotations":{"bold":false,"italic":false,"strikethrough":false,"underline":false,"code":false,"color":"default"},"plain_text":"src/echo.pipe.spec.ts","href":null}],"color":"default"}},{"object":"block","id":"23b52fb4-2bdf-441b-aa10-f74e888573ba","parent":{"type":"page_id","page_id":"ba94cfed-9b64-41d3-862b-55c25fe0cea7"},"created_time":"2023-05-21T00:22:00.000Z","last_edited_time":"2023-05-21T01:36:00.000Z","created_by":{"object":"user","id":"f4f222d4-d508-405d-ba6c-da82ee26ee54"},"last_edited_by":{"object":"user","id":"f4f222d4-d508-405d-ba6c-da82ee26ee54"},"has_children":false,"archived":false,"in_trash":false,"type":"code","code":{"caption":[],"rich_text":[{"type":"text","text":{"content":"import { Component } from \"@angular/core\";\nimport { TestBed, async } from \"@angular/core/testing\";\nimport { EchoPipe } from \"./echo.pipe\";\n@Component({\n  selector: \"test\",\n  template: `\n    <p>{{ text | echo }}</p>\n  `\n})\nclass TestComponent {\n  text: string;\n}\ndescribe(\"EchoPipe\", () => {\n  beforeEach(() => {\n    TestBed.configureTestingModule({\n      declarations: [TestComponent, EchoPipe]\n    });\n  });\n  beforeEach(async(() => {\n    TestBed.compileComponents();\n  }));\n  it(\"works well\", async(() => {\n    const fixture = TestBed.createComponent(TestComponent);\n    fixture.componentInstance.text = \"foo\";\n    fixture.detectChanges();\n    const el = fixture.debugElement.nativeElement as HTMLElement;\n    expect(el.querySelector(\"p\").textContent).toBe(\"foo\");\n  }));\n});","link":null},"annotations":{"bold":false,"italic":false,"strikethrough":false,"underline":false,"code":false,"color":"default"},"plain_text":"import { Component } from \"@angular/core\";\nimport { TestBed, async } from \"@angular/core/testing\";\nimport { EchoPipe } from \"./echo.pipe\";\n@Component({\n  selector: \"test\",\n  template: `\n    <p>{{ text | echo }}</p>\n  `\n})\nclass TestComponent {\n  text: string;\n}\ndescribe(\"EchoPipe\", () => {\n  beforeEach(() => {\n    TestBed.configureTestingModule({\n      declarations: [TestComponent, EchoPipe]\n    });\n  });\n  beforeEach(async(() => {\n    TestBed.compileComponents();\n  }));\n  it(\"works well\", async(() => {\n    const fixture = TestBed.createComponent(TestComponent);\n    fixture.componentInstance.text = \"foo\";\n    fixture.detectChanges();\n    const el = fixture.debugElement.nativeElement as HTMLElement;\n    expect(el.querySelector(\"p\").textContent).toBe(\"foo\");\n  }));\n});","href":null}],"language":"plain text"}},{"object":"block","id":"15fe03dd-b356-426d-bb65-3ae7e318df8c","parent":{"type":"page_id","page_id":"ba94cfed-9b64-41d3-862b-55c25fe0cea7"},"created_time":"2023-05-21T00:22:00.000Z","last_edited_time":"2023-05-21T00:22:00.000Z","created_by":{"object":"user","id":"f4f222d4-d508-405d-ba6c-da82ee26ee54"},"last_edited_by":{"object":"user","id":"f4f222d4-d508-405d-ba6c-da82ee26ee54"},"has_children":false,"archived":false,"in_trash":false,"type":"paragraph","paragraph":{"rich_text":[{"type":"text","text":{"content":"At last, load that spec from src/main.spec.ts. ","link":null},"annotations":{"bold":false,"italic":false,"strikethrough":false,"underline":false,"code":false,"color":"default"},"plain_text":"At last, load that spec from src/main.spec.ts. ","href":null},{"type":"text","text":{"content":"require.context","link":null},"annotations":{"bold":true,"italic":false,"strikethrough":false,"underline":false,"code":false,"color":"default"},"plain_text":"require.context","href":null},{"type":"text","text":{"content":" is very useful utility of webpack that can load all modules in directory recursively.","link":null},"annotations":{"bold":false,"italic":false,"strikethrough":false,"underline":false,"code":false,"color":"default"},"plain_text":" is very useful utility of webpack that can load all modules in directory recursively.","href":null}],"color":"default"}},{"object":"block","id":"f5f0dc5d-7cae-46a5-b738-3b16a3b968cc","parent":{"type":"page_id","page_id":"ba94cfed-9b64-41d3-862b-55c25fe0cea7"},"created_time":"2023-05-21T00:22:00.000Z","last_edited_time":"2023-05-21T01:37:00.000Z","created_by":{"object":"user","id":"f4f222d4-d508-405d-ba6c-da82ee26ee54"},"last_edited_by":{"object":"user","id":"f4f222d4-d508-405d-ba6c-da82ee26ee54"},"has_children":false,"archived":false,"in_trash":false,"type":"code","code":{"caption":[],"rich_text":[{"type":"text","text":{"content":"// TestBed initialization\n// ...\n// load all specs in ./src\nconst context = (require as any).context(\"./\", true, /\\.spec\\.ts$/);\ncontext.keys().map(context);","link":null},"annotations":{"bold":false,"italic":false,"strikethrough":false,"underline":false,"code":false,"color":"default"},"plain_text":"// TestBed initialization\n// ...\n// load all specs in ./src\nconst context = (require as any).context(\"./\", true, /\\.spec\\.ts$/);\ncontext.keys().map(context);","href":null}],"language":"plain text"}},{"object":"block","id":"11347504-52a3-4656-b122-37f8bbe280d6","parent":{"type":"page_id","page_id":"ba94cfed-9b64-41d3-862b-55c25fe0cea7"},"created_time":"2023-05-21T00:22:00.000Z","last_edited_time":"2023-05-21T00:22:00.000Z","created_by":{"object":"user","id":"f4f222d4-d508-405d-ba6c-da82ee26ee54"},"last_edited_by":{"object":"user","id":"f4f222d4-d508-405d-ba6c-da82ee26ee54"},"has_children":false,"archived":false,"in_trash":false,"type":"heading_2","heading_2":{"rich_text":[{"type":"text","text":{"content":"More things","link":null},"annotations":{"bold":false,"italic":false,"strikethrough":false,"underline":false,"code":false,"color":"default"},"plain_text":"More things","href":null}],"is_toggleable":false,"color":"default"}},{"object":"block","id":"6bf2a56d-338a-48ef-b0ee-993d3533f757","parent":{"type":"page_id","page_id":"ba94cfed-9b64-41d3-862b-55c25fe0cea7"},"created_time":"2023-05-21T00:22:00.000Z","last_edited_time":"2023-05-21T00:22:00.000Z","created_by":{"object":"user","id":"f4f222d4-d508-405d-ba6c-da82ee26ee54"},"last_edited_by":{"object":"user","id":"f4f222d4-d508-405d-ba6c-da82ee26ee54"},"has_children":false,"archived":false,"in_trash":false,"type":"paragraph","paragraph":{"rich_text":[{"type":"text","text":{"content":"Official documentation for testing","link":{"url":"https://angular.io/docs/ts/latest/guide/testing.html"}},"annotations":{"bold":false,"italic":false,"strikethrough":false,"underline":false,"code":false,"color":"default"},"plain_text":"Official documentation for testing","href":"https://angular.io/docs/ts/latest/guide/testing.html"},{"type":"text","text":{"content":" is a very good article. You can trying it with the testing environment which we’ve created here.","link":null},"annotations":{"bold":false,"italic":false,"strikethrough":false,"underline":false,"code":false,"color":"default"},"plain_text":" is a very good article. You can trying it with the testing environment which we’ve created here.","href":null}],"color":"default"}},{"object":"block","id":"00a338ad-bc8e-48f6-960d-7cee776e1fec","parent":{"type":"page_id","page_id":"ba94cfed-9b64-41d3-862b-55c25fe0cea7"},"created_time":"2023-05-21T00:22:00.000Z","last_edited_time":"2023-05-21T00:22:00.000Z","created_by":{"object":"user","id":"f4f222d4-d508-405d-ba6c-da82ee26ee54"},"last_edited_by":{"object":"user","id":"f4f222d4-d508-405d-ba6c-da82ee26ee54"},"has_children":false,"archived":false,"in_trash":false,"type":"heading_2","heading_2":{"rich_text":[{"type":"text","text":{"content":"Conclusion","link":null},"annotations":{"bold":false,"italic":false,"strikethrough":false,"underline":false,"code":false,"color":"default"},"plain_text":"Conclusion","href":null}],"is_toggleable":false,"color":"default"}},{"object":"block","id":"820275a9-8b0c-4b4d-a51a-0bf58f5a1898","parent":{"type":"page_id","page_id":"ba94cfed-9b64-41d3-862b-55c25fe0cea7"},"created_time":"2023-05-21T00:22:00.000Z","last_edited_time":"2023-05-21T00:22:00.000Z","created_by":{"object":"user","id":"f4f222d4-d508-405d-ba6c-da82ee26ee54"},"last_edited_by":{"object":"user","id":"f4f222d4-d508-405d-ba6c-da82ee26ee54"},"has_children":false,"archived":false,"in_trash":false,"type":"bulleted_list_item","bulleted_list_item":{"rich_text":[{"type":"text","text":{"content":"karma-webpack","link":null},"annotations":{"bold":true,"italic":false,"strikethrough":false,"underline":false,"code":false,"color":"default"},"plain_text":"karma-webpack","href":null},{"type":"text","text":{"content":" and sourcemap are awesome.","link":null},"annotations":{"bold":false,"italic":false,"strikethrough":false,"underline":false,"code":false,"color":"default"},"plain_text":" and sourcemap are awesome.","href":null}],"color":"default"}},{"object":"block","id":"50dc6131-9aa7-4d97-aeb1-76de47bfb8e9","parent":{"type":"page_id","page_id":"ba94cfed-9b64-41d3-862b-55c25fe0cea7"},"created_time":"2023-05-21T00:22:00.000Z","last_edited_time":"2023-05-21T00:22:00.000Z","created_by":{"object":"user","id":"f4f222d4-d508-405d-ba6c-da82ee26ee54"},"last_edited_by":{"object":"user","id":"f4f222d4-d508-405d-ba6c-da82ee26ee54"},"has_children":false,"archived":false,"in_trash":false,"type":"bulleted_list_item","bulleted_list_item":{"rich_text":[{"type":"text","text":{"content":"Create a testing entry point and initialize ","link":null},"annotations":{"bold":false,"italic":false,"strikethrough":false,"underline":false,"code":false,"color":"default"},"plain_text":"Create a testing entry point and initialize ","href":null},{"type":"text","text":{"content":"TestBed","link":null},"annotations":{"bold":true,"italic":false,"strikethrough":false,"underline":false,"code":false,"color":"default"},"plain_text":"TestBed","href":null}],"color":"default"}},{"object":"block","id":"6d479ecc-b76e-44fb-b063-e2e0adfa6680","parent":{"type":"page_id","page_id":"ba94cfed-9b64-41d3-862b-55c25fe0cea7"},"created_time":"2023-05-21T00:22:00.000Z","last_edited_time":"2023-05-21T00:22:00.000Z","created_by":{"object":"user","id":"f4f222d4-d508-405d-ba6c-da82ee26ee54"},"last_edited_by":{"object":"user","id":"f4f222d4-d508-405d-ba6c-da82ee26ee54"},"has_children":false,"archived":false,"in_trash":false,"type":"bulleted_list_item","bulleted_list_item":{"rich_text":[{"type":"text","text":{"content":"Write tests!","link":null},"annotations":{"bold":false,"italic":false,"strikethrough":false,"underline":false,"code":false,"color":"default"},"plain_text":"Write tests!","href":null}],"color":"default"}},{"object":"block","id":"18dfb84b-be8a-43c8-bdb4-c653bacd37ec","parent":{"type":"page_id","page_id":"ba94cfed-9b64-41d3-862b-55c25fe0cea7"},"created_time":"2023-05-21T00:22:00.000Z","last_edited_time":"2023-05-21T00:22:00.000Z","created_by":{"object":"user","id":"f4f222d4-d508-405d-ba6c-da82ee26ee54"},"last_edited_by":{"object":"user","id":"f4f222d4-d508-405d-ba6c-da82ee26ee54"},"has_children":false,"archived":false,"in_trash":false,"type":"paragraph","paragraph":{"rich_text":[{"type":"text","text":{"content":"Source code in this article is at ","link":null},"annotations":{"bold":false,"italic":false,"strikethrough":false,"underline":false,"code":false,"color":"default"},"plain_text":"Source code in this article is at ","href":null},{"type":"text","text":{"content":"GitHub","link":{"url":"https://github.com/laco0416/ng2-test-seed"}},"annotations":{"bold":false,"italic":false,"strikethrough":false,"underline":false,"code":false,"color":"default"},"plain_text":"GitHub","href":"https://github.com/laco0416/ng2-test-seed"}],"color":"default"}}]